Project01/extension/counter.vhd
-- Quartus II VHDL Template
-- Binary Counter
-- modified by Maxwell S16

library ieee;
use ieee.std_logic_1164.all;
use ieee.numeric_std.all;

entity counter is

  port
    (
      clk         : in std_logic;
      reset	  : in std_logic;
      enable	  : in std_logic;
      q		  : out std_logic_vector (4 downto 0)
      );

end entity;

architecture rtl of counter is

  signal   cnt	: unsigned (4 downto 0);

begin

  process (clk)
  begin
    if reset = '1' then
      -- Reset the counter to 0
      cnt <= "00000";
    elsif (rising_edge(clk)) then
      if enable = '1' then
        -- Increment the counter if counting is enabled			   
        cnt <= cnt + 1;
      end if;
    end if;
  end process;

  q <= std_logic_vector(cnt);

end rtl;

Project01/extension/extension.vhd
-- Copyright (C) 1991-2012 Altera Corporation
-- Your use of Altera Corporation's design tools, logic functions 
-- and other software and tools, and its AMPP partner logic 
-- functions, and any output files from any of the foregoing 
-- (including device programming or simulation files), and any 
-- associated documentation or information are expressly subject 
-- to the terms and conditions of the Altera Program License 
-- Subscription Agreement, Altera MegaCore Function License 
-- Agreement, or other applicable license agreement, including, 
-- without limitation, that your use is for the sole purpose of 
-- programming logic devices manufactured by Altera and sold by 
-- Altera or its authorized distributors.  Please refer to the 
-- applicable agreement for further details.

-- PROGRAM		"Quartus II 32-bit"
-- VERSION		"Version 12.1 Build 177 11/07/2012 SJ Full Version"
-- CREATED		"Mon Sep 26 13:48:46 2022"

LIBRARY ieee;
USE ieee.std_logic_1164.all; 

LIBRARY work;

ENTITY extension IS 
	PORT
	(
		clk :  IN  STD_LOGIC;
		reset :  IN  STD_LOGIC;
		enable :  IN  STD_LOGIC;
		f :  OUT  STD_LOGIC
	);
END extension;

ARCHITECTURE bdf_type OF extension IS 

COMPONENT counter
	PORT(clk : IN STD_LOGIC;
		 reset : IN STD_LOGIC;
		 enable : IN STD_LOGIC;
		 q : OUT STD_LOGIC_VECTOR(4 DOWNTO 0)
	);
END COMPONENT;

SIGNAL	q :  STD_LOGIC_VECTOR(4 DOWNTO 0);
SIGNAL	SYNTHESIZED_WIRE_0 :  STD_LOGIC;
SIGNAL	SYNTHESIZED_WIRE_1 :  STD_LOGIC;
SIGNAL	SYNTHESIZED_WIRE_2 :  STD_LOGIC;
SIGNAL	SYNTHESIZED_WIRE_3 :  STD_LOGIC;
SIGNAL	SYNTHESIZED_WIRE_4 :  STD_LOGIC;
SIGNAL	SYNTHESIZED_WIRE_5 :  STD_LOGIC;
SIGNAL	SYNTHESIZED_WIRE_6 :  STD_LOGIC;
SIGNAL	SYNTHESIZED_WIRE_7 :  STD_LOGIC;
SIGNAL	SYNTHESIZED_WIRE_8 :  STD_LOGIC;
SIGNAL	SYNTHESIZED_WIRE_9 :  STD_LOGIC;
SIGNAL	SYNTHESIZED_WIRE_10 :  STD_LOGIC;
SIGNAL	SYNTHESIZED_WIRE_11 :  STD_LOGIC;
SIGNAL	SYNTHESIZED_WIRE_12 :  STD_LOGIC;
SIGNAL	SYNTHESIZED_WIRE_13 :  STD_LOGIC;
SIGNAL	SYNTHESIZED_WIRE_14 :  STD_LOGIC;
SIGNAL	SYNTHESIZED_WIRE_15 :  STD_LOGIC;


BEGIN 



SYNTHESIZED_WIRE_4 <= SYNTHESIZED_WIRE_0 AND q(1) AND q(0);


b2v_inst0 : counter
PORT MAP(clk => clk,
		 reset => reset,
		 enable => enable,
		 q => q);


SYNTHESIZED_WIRE_0 <= NOT(q(3));



SYNTHESIZED_WIRE_14 <= NOT(q(4));



SYNTHESIZED_WIRE_15 <= NOT(q(1));



SYNTHESIZED_WIRE_9 <= SYNTHESIZED_WIRE_1 AND SYNTHESIZED_WIRE_2 AND SYNTHESIZED_WIRE_3 AND q(1);


SYNTHESIZED_WIRE_1 <= NOT(q(4));



SYNTHESIZED_WIRE_3 <= NOT(q(2));



SYNTHESIZED_WIRE_2 <= NOT(q(3));



f <= SYNTHESIZED_WIRE_4 OR SYNTHESIZED_WIRE_5 OR SYNTHESIZED_WIRE_6 OR SYNTHESIZED_WIRE_7 OR SYNTHESIZED_WIRE_8 OR SYNTHESIZED_WIRE_9;


SYNTHESIZED_WIRE_6 <= q(4) AND q(3) AND q(2) AND q(0);


SYNTHESIZED_WIRE_5 <= q(4) AND SYNTHESIZED_WIRE_10 AND SYNTHESIZED_WIRE_11 AND q(0);


SYNTHESIZED_WIRE_10 <= NOT(q(3));



SYNTHESIZED_WIRE_11 <= NOT(q(2));



SYNTHESIZED_WIRE_7 <= SYNTHESIZED_WIRE_12 AND SYNTHESIZED_WIRE_13 AND q(1) AND q(0);


SYNTHESIZED_WIRE_12 <= NOT(q(4));



SYNTHESIZED_WIRE_13 <= NOT(q(2));



SYNTHESIZED_WIRE_8 <= SYNTHESIZED_WIRE_14 AND q(2) AND SYNTHESIZED_WIRE_15 AND q(0);


END bdf_type;

Project01/extension/extbench.vhd
-- Stephanie R Taylor
-- Fall 2020
-- CS 232
--
-- test program for the ext light simulation
-- shows how to create a clock using a loop

library ieee;
use ieee.std_logic_1164.all;
use ieee.numeric_std.all;

entity extbench is
end entity;

architecture test of extbench is
  constant num_cycles : integer := 33;  -- run for 40 clock cycles

  -- this circuit needs a clock, enable, and a reset
  -- for the counter
  signal clk    : std_logic := '1';
  signal enable : std_logic;
  signal reset  : std_logic;
  signal f	 : std_logic;
 
  component extension
  port(
  		clk :  IN  STD_LOGIC;
		reset :  IN  STD_LOGIC;
		enable :  IN  STD_LOGIC;
		f :  OUT  STD_LOGIC
		);
  end component;

  begin

  -- start off with a short reset
  reset <= '1', '0' after 5 ns;

  enable <= '1';

  -- create a clock
  process begin
    for i in 1 to num_cycles loop
      clk <= not clk;
      wait for 1 ns;
      clk <= not clk;
      wait for 1 ns;
    end loop;
    wait;
  end process;

  -- port map the circuit
  -- Make sure the list of inputs here has signals declared above (all the ones here now have been).
  -- Also make sure the order matches that from the port definition of the ext
  -- component.
  L0: extension port map( clk, reset, enable, f);

end test;

Project01/extension/extbench.vcd
$date
  Mon Sep 26 21:32:32 2022
$end
$version
  GHDL v0
$end
$timescale
  1 fs
$end
$scope module standard $end
$upscope $end
$scope module std_logic_1164 $end
$upscope $end
$scope module numeric_std $end
$upscope $end
$scope module extbench $end
$var reg 1 ! clk $end
$var reg 1 " enable $end
$var reg 1 # reset $end
$var reg 1 $ f $end
$scope module l0 $end
$var reg 1 % clk $end
$var reg 1 & reset $end
$var reg 1 ' enable $end
$var reg 1 ( f $end
$var reg 5 ) q[4:0] $end
$var reg 1 * synthesized_wire_0 $end
$var reg 1 + synthesized_wire_1 $end
$var reg 1 , synthesized_wire_2 $end
$var reg 1 - synthesized_wire_3 $end
$var reg 1 . synthesized_wire_4 $end
$var reg 1 / synthesized_wire_5 $end
$var reg 1 0 synthesized_wire_6 $end
$var reg 1 1 synthesized_wire_7 $end
$var reg 1 2 synthesized_wire_8 $end
$var reg 1 3 synthesized_wire_9 $end
$var reg 1 4 synthesized_wire_10 $end
$var reg 1 5 synthesized_wire_11 $end
$var reg 1 6 synthesized_wire_12 $end
$var reg 1 7 synthesized_wire_13 $end
$var reg 1 8 synthesized_wire_14 $end
$var reg 1 9 synthesized_wire_15 $end
$scope module b2v_inst0 $end
$var reg 1 : clk $end
$var reg 1 ; reset $end
$var reg 1 < enable $end
$var reg 5 = q[4:0] $end
$var reg 5 > cnt[4:0] $end
$upscope $end
$upscope $end
$upscope $end
$enddefinitions $end
#0
0!
1"
1#
0$
0%
1&
1'
0(
b00000 )
1*
1+
1,
1-
0.
0/
00
01
02
03
14
15
16
17
18
19
0:
1;
1<
b00000 =
b00000 >
#1000000
1!
1%
1:
#2000000
0!
0%
0:
#3000000
1!
1%
1:
#4000000
0!
0%
0:
#5000000
1!
0#
1%
0&
b00001 )
1:
0;
b00001 =
b00001 >
#6000000
0!
0%
0:
#7000000
1!
1$
1%
1(
b00010 )
13
09
1:
b00010 =
b00010 >
#8000000
0!
0%
0:
#9000000
1!
1%
b00011 )
1.
11
1:
b00011 =
b00011 >
#10000000
0!
0%
0:
#11000000
1!
0$
1%
0(
b00100 )
0-
0.
01
03
05
07
19
1:
b00100 =
b00100 >
#12000000
0!
0%
0:
#13000000
1!
1$
1%
1(
b00101 )
12
1:
b00101 =
b00101 >
#14000000
0!
0%
0:
#15000000
1!
0$
1%
0(
b00110 )
02
09
1:
b00110 =
b00110 >
#16000000
0!
0%
0:
#17000000
1!
1$
1%
1(
b00111 )
1.
1:
b00111 =
b00111 >
#18000000
0!
0%
0:
#19000000
1!
0$
1%
0(
b01000 )
0*
0,
1-
0.
04
15
17
19
1:
b01000 =
b01000 >
#20000000
0!
0%
0:
#21000000
1!
1%
b01001 )
1:
b01001 =
b01001 >
#22000000
0!
0%
0:
#23000000
1!
1%
b01010 )
09
1:
b01010 =
b01010 >
#24000000
0!
0%
0:
#25000000
1!
1$
1%
1(
b01011 )
11
1:
b01011 =
b01011 >
#26000000
0!
0%
0:
#27000000
1!
0$
1%
0(
b01100 )
0-
01
05
07
19
1:
b01100 =
b01100 >
#28000000
0!
0%
0:
#29000000
1!
1$
1%
1(
b01101 )
12
1:
b01101 =
b01101 >
#30000000
0!
0%
0:
#31000000
1!
0$
1%
0(
b01110 )
02
09
1:
b01110 =
b01110 >
#32000000
0!
0%
0:
#33000000
1!
1%
b01111 )
1:
b01111 =
b01111 >
#34000000
0!
0%
0:
#35000000
1!
1%
b10000 )
1*
0+
1,
1-
14
15
06
17
08
19
1:
b10000 =
b10000 >
#36000000
0!
0%
0:
#37000000
1!
1$
1%
1(
b10001 )
1/
1:
b10001 =
b10001 >
#38000000
0!
0%
0:
#39000000
1!
0$
1%
0(
b10010 )
0/
09
1:
b10010 =
b10010 >
#40000000
0!
0%
0:
#41000000
1!
1$
1%
1(
b10011 )
1.
1/
1:
b10011 =
b10011 >
#42000000
0!
0%
0:
#43000000
1!
0$
1%
0(
b10100 )
0-
0.
0/
05
07
19
1:
b10100 =
b10100 >
#44000000
0!
0%
0:
#45000000
1!
1%
b10101 )
1:
b10101 =
b10101 >
#46000000
0!
0%
0:
#47000000
1!
1%
b10110 )
09
1:
b10110 =
b10110 >
#48000000
0!
0%
0:
#49000000
1!
1$
1%
1(
b10111 )
1.
1:
b10111 =
b10111 >
#50000000
0!
0%
0:
#51000000
1!
0$
1%
0(
b11000 )
0*
0,
1-
0.
04
15
17
19
1:
b11000 =
b11000 >
#52000000
0!
0%
0:
#53000000
1!
1%
b11001 )
1:
b11001 =
b11001 >
#54000000
0!
0%
0:
#55000000
1!
1%
b11010 )
09
1:
b11010 =
b11010 >
#56000000
0!
0%
0:
#57000000
1!
1%
b11011 )
1:
b11011 =
b11011 >
#58000000
0!
0%
0:
#59000000
1!
1%
b11100 )
0-
05
07
19
1:
b11100 =
b11100 >
#60000000
0!
0%
0:
#61000000
1!
1$
1%
1(
b11101 )
10
1:
b11101 =
b11101 >
#62000000
0!
0%
0:
#63000000
1!
0$
1%
0(
b11110 )
00
09
1:
b11110 =
b11110 >
#64000000
0!
0%
0:
#65000000
1!
1$
1%
1(
b11111 )
10
1:
b11111 =
b11111 >
