Project04/lightrom.vhd
library IEEE;
use IEEE.std_logic_1164.all;
use IEEE.numeric_std.all;

entity lightrom is
	port (
			addr  : in std_logic_vector(4 downto 0);
			data	: out std_logic_vector(3 downto 0)
			);
end lightrom;

architecture one of lightrom is 
begin
data <= 
      "0000" when addr = "00000" else -- move 0s to LR  00000000
      "0101" when addr = "00001" else -- bit invert LR  11111111
      "0001" when addr = "00010" else -- shift LR right 01111111
      "0100" when addr = "00011" else -- sub 1 from LR  01111110
      "0001" when addr = "00100" else -- shift LR right 00111111
      "0100" when addr = "00101" else -- sub 1 from LR  00111110
      "0001" when addr = "00110" else -- shift LR right 00011111
      "0100" when addr = "00111" else -- sub 1 from LR  00011110
      "0001" when addr = "01000" else -- shift LR right 00001111
      "0100" when addr = "01001" else -- sub 1 from LR  00001110
      "0001" when addr = "01010" else -- shift LR right 00000111
      "0100" when addr = "01011" else -- sub 1 from LR  00000110
      "0001" when addr = "01100" else -- shift LR right 00000011
      "0100" when addr = "01101" else -- sub 1 from LR  00000010
      "0001" when addr = "01110" else -- shift LR right 00000001
      "0100";
end one;

Project04/lights.vhd
-- Quartus II VHDL Template
-- Four-State Moore State Machine

-- A Moore machine's outputs are dependent only on the current state.
-- The output is written only when the state changes.  (State
-- transitions are synchronous.)

library ieee;
use ieee.std_logic_1164.all;
use ieee.numeric_std.all;

entity lights is

	port(
		clk		 : in	std_logic;
		reset	 	 : in	std_logic;
		lightsig	 : out std_logic_vector(7 downto 0);
		IRView	 : out std_logic_vector(3 downto 0)
		--PCView	 : out std_logic_vector(3 downto 0)
	);

end entity;

architecture rtl of lights is

	signal IR	: std_logic_vector(3 downto 0);
	signal PC	: unsigned(4 downto 0);
	signal LR	: unsigned(7 downto 0);
	signal ROMvalue	: std_logic_vector(3 downto 0);
	signal L		: unsigned(3 downto 0);
	signal R		: unsigned(3 downto 0);

	-- Build an enumerated type for the state machine
	type state_type is (sFetch, sExecute);

	-- Register to hold the current state
	signal state   : state_type;
	
component lightrom
    port (
			addr  : in std_logic_vector(4 downto 0);
			data	: out std_logic_vector(3 downto 0)
	 );
end component;

begin

	lightrom1 : lightrom
	port map(
		addr => std_logic_vector(PC),
		data => ROMvalue
	);

	-- Logic to advance to the next state
	process (clk, reset)
	begin
		if reset = '0' then
			state <= sFetch;
			PC <= (others=>'0');
			IR <= (others=>'0');
			LR <= (others=>'0');
		elsif (rising_edge(clk)) then
			case state is
				when sFetch=>
					IR <= ROMvalue;
					PC <= PC + 1;
					state <= sExecute;
				when sExecute=>
					case IR is
						when "0000" =>
							LR <= (others=>'0');
							state <= sFetch;
						when "0001" =>
							LR <= LR srl 1;
							state <= sFetch;
						when "0010" =>
							LR <= LR sll 1;
							state <= sFetch;
						when "0011" =>
							LR <= LR + 1;
							state <= sFetch;
						when "0100" =>
							LR <= LR - 1;
							state <= sFetch;
						when "0101" =>
							LR <= not LR;
							state <= sFetch;
						when "0110" =>
							LR <= LR ror 1;
							state <= sFetch;
						when "0111" =>
							LR <= LR rol 1;
							state <= sFetch;
						when "1000" =>
							LR <= "11111111";
							state <= sFetch;
						when "1001" =>
							L <= LR(7 downto 4) sll 1;
							R <= LR(3 downto 0) srl 1;
							LR <= L & R;
							state <= sFetch;
						when others =>
							LR <= LR;
					end case;
			end case;
		end if;
	end process;

	lightsig <= std_logic_vector(LR);
	IRView <= IR;
	
end rtl;

Project04/lightsbench.vhd
-- Bruce A. Maxwell
-- Spring 2013
-- CS 232
--
-- test program for the lights circuit
--

library ieee;
use ieee.std_logic_1164.all;
use ieee.numeric_std.all;

entity lightsbench is
end entity;

architecture test of lightsbench is
  constant num_cycles : integer := 70;

  -- this circuit just needs a clock and a reset
  signal clk : std_logic := '1';
  signal reset : std_logic;

  -- lights component
  component lights
    port( clk, reset : in std_logic;
          lightsig   : out std_logic_vector(7 downto 0);
          IRView     : out std_logic_vector(3 downto 0) );
  end component;

  -- output signals
  signal lightsig : std_logic_vector(7 downto 0);
  signal irview : std_logic_vector(3 downto 0);

begin

  -- start off with a short reset
  reset <= '0', '1' after 5 ns;

  -- create a clock
  process begin
    for i in 1 to num_cycles loop
      clk <= not clk;
      wait for 5 ns;
      clk <= not clk;
      wait for 5 ns;
    end loop;
    wait;
  end process;

  -- port map the circuit
  L0: lights port map( clk, reset, lightsig, irview );

end test;

Project04/lightsbench.vcd
$date
  Mon Oct 24 16:36:52 2022
$end
$version
  GHDL v0
$end
$timescale
  1 fs
$end
$scope module standard $end
$upscope $end
$scope module std_logic_1164 $end
$upscope $end
$scope module numeric_std $end
$upscope $end
$scope module lightsbench $end
$var reg 1 ! clk $end
$var reg 1 " reset $end
$var reg 8 # lightsig[7:0] $end
$var reg 4 $ irview[3:0] $end
$scope module l0 $end
$var reg 1 % clk $end
$var reg 1 & reset $end
$var reg 8 ' lightsig[7:0] $end
$var reg 4 ( irview[3:0] $end
$var reg 4 ) ir[3:0] $end
$var reg 5 * pc[4:0] $end
$var reg 8 + lr[7:0] $end
$var reg 4 , romvalue[3:0] $end
$var reg 4 - l[3:0] $end
$var reg 4 . r[3:0] $end
$comment state is not handled $end
$scope module lightrom1 $end
$var reg 5 / addr[4:0] $end
$var reg 4 0 data[3:0] $end
$upscope $end
$upscope $end
$upscope $end
$enddefinitions $end
#0
0!
0"
b00000000 #
b0000 $
0%
0&
b00000000 '
b0000 (
b0000 )
b00000 *
b00000000 +
b0000 ,
bUUUU -
bUUUU .
b00000 /
b0000 0
#5000000
1!
1"
1%
1&
b00001 *
b0101 ,
b00001 /
b0101 0
#10000000
0!
0%
#15000000
1!
1%
#20000000
0!
0%
#25000000
1!
b0101 $
1%
b0101 (
b0101 )
b00010 *
b0001 ,
b00010 /
b0001 0
#30000000
0!
0%
#35000000
1!
b11111111 #
1%
b11111111 '
b11111111 +
#40000000
0!
0%
#45000000
1!
b0001 $
1%
b0001 (
b0001 )
b00011 *
b0100 ,
b00011 /
b0100 0
#50000000
0!
0%
#55000000
1!
b01111111 #
1%
b01111111 '
b01111111 +
#60000000
0!
0%
#65000000
1!
b0100 $
1%
b0100 (
b0100 )
b00100 *
b0001 ,
b00100 /
b0001 0
#70000000
0!
0%
#75000000
1!
b01111110 #
1%
b01111110 '
b01111110 +
#80000000
0!
0%
#85000000
1!
b0001 $
1%
b0001 (
b0001 )
b00101 *
b0100 ,
b00101 /
b0100 0
#90000000
0!
0%
#95000000
1!
b00111111 #
1%
b00111111 '
b00111111 +
#100000000
0!
0%
#105000000
1!
b0100 $
1%
b0100 (
b0100 )
b00110 *
b0001 ,
b00110 /
b0001 0
#110000000
0!
0%
#115000000
1!
b00111110 #
1%
b00111110 '
b00111110 +
#120000000
0!
0%
#125000000
1!
b0001 $
1%
b0001 (
b0001 )
b00111 *
b0100 ,
b00111 /
b0100 0
#130000000
0!
0%
#135000000
1!
b00011111 #
1%
b00011111 '
b00011111 +
#140000000
0!
0%
#145000000
1!
b0100 $
1%
b0100 (
b0100 )
b01000 *
b0001 ,
b01000 /
b0001 0
#150000000
0!
0%
#155000000
1!
b00011110 #
1%
b00011110 '
b00011110 +
#160000000
0!
0%
#165000000
1!
b0001 $
1%
b0001 (
b0001 )
b01001 *
b0100 ,
b01001 /
b0100 0
#170000000
0!
0%
#175000000
1!
b00001111 #
1%
b00001111 '
b00001111 +
#180000000
0!
0%
#185000000
1!
b0100 $
1%
b0100 (
b0100 )
b01010 *
b0001 ,
b01010 /
b0001 0
#190000000
0!
0%
#195000000
1!
b00001110 #
1%
b00001110 '
b00001110 +
#200000000
0!
0%
#205000000
1!
b0001 $
1%
b0001 (
b0001 )
b01011 *
b0100 ,
b01011 /
b0100 0
#210000000
0!
0%
#215000000
1!
b00000111 #
1%
b00000111 '
b00000111 +
#220000000
0!
0%
#225000000
1!
b0100 $
1%
b0100 (
b0100 )
b01100 *
b0001 ,
b01100 /
b0001 0
#230000000
0!
0%
#235000000
1!
b00000110 #
1%
b00000110 '
b00000110 +
#240000000
0!
0%
#245000000
1!
b0001 $
1%
b0001 (
b0001 )
b01101 *
b0100 ,
b01101 /
b0100 0
#250000000
0!
0%
#255000000
1!
b00000011 #
1%
b00000011 '
b00000011 +
#260000000
0!
0%
#265000000
1!
b0100 $
1%
b0100 (
b0100 )
b01110 *
b0001 ,
b01110 /
b0001 0
#270000000
0!
0%
#275000000
1!
b00000010 #
1%
b00000010 '
b00000010 +
#280000000
0!
0%
#285000000
1!
b0001 $
1%
b0001 (
b0001 )
b01111 *
b0100 ,
b01111 /
b0100 0
#290000000
0!
0%
#295000000
1!
b00000001 #
1%
b00000001 '
b00000001 +
#300000000
0!
0%
#305000000
1!
b0100 $
1%
b0100 (
b0100 )
b10000 *
b10000 /
#310000000
0!
0%
#315000000
1!
b00000000 #
1%
b00000000 '
b00000000 +
#320000000
0!
0%
#325000000
1!
1%
b10001 *
b10001 /
#330000000
0!
0%
#335000000
1!
b11111111 #
1%
b11111111 '
b11111111 +
#340000000
0!
0%
#345000000
1!
1%
b10010 *
b10010 /
#350000000
0!
0%
#355000000
1!
b11111110 #
1%
b11111110 '
b11111110 +
#360000000
0!
0%
#365000000
1!
1%
b10011 *
b10011 /
#370000000
0!
0%
#375000000
1!
b11111101 #
1%
b11111101 '
b11111101 +
#380000000
0!
0%
#385000000
1!
1%
b10100 *
b10100 /
#390000000
0!
0%
#395000000
1!
b11111100 #
1%
b11111100 '
b11111100 +
#400000000
0!
0%
#405000000
1!
1%
b10101 *
b10101 /
#410000000
0!
0%
#415000000
1!
b11111011 #
1%
b11111011 '
b11111011 +
#420000000
0!
0%
#425000000
1!
1%
b10110 *
b10110 /
#430000000
0!
0%
#435000000
1!
b11111010 #
1%
b11111010 '
b11111010 +
#440000000
0!
0%
#445000000
1!
1%
b10111 *
b10111 /
#450000000
0!
0%
#455000000
1!
b11111001 #
1%
b11111001 '
b11111001 +
#460000000
0!
0%
#465000000
1!
1%
b11000 *
b11000 /
#470000000
0!
0%
#475000000
1!
b11111000 #
1%
b11111000 '
b11111000 +
#480000000
0!
0%
#485000000
1!
1%
b11001 *
b11001 /
#490000000
0!
0%
#495000000
1!
b11110111 #
1%
b11110111 '
b11110111 +
#500000000
0!
0%
#505000000
1!
1%
b11010 *
b11010 /
#510000000
0!
0%
#515000000
1!
b11110110 #
1%
b11110110 '
b11110110 +
#520000000
0!
0%
#525000000
1!
1%
b11011 *
b11011 /
#530000000
0!
0%
#535000000
1!
b11110101 #
1%
b11110101 '
b11110101 +
#540000000
0!
0%
#545000000
1!
1%
b11100 *
b11100 /
#550000000
0!
0%
#555000000
1!
b11110100 #
1%
b11110100 '
b11110100 +
#560000000
0!
0%
#565000000
1!
1%
b11101 *
b11101 /
#570000000
0!
0%
#575000000
1!
b11110011 #
1%
b11110011 '
b11110011 +
#580000000
0!
0%
#585000000
1!
1%
b11110 *
b11110 /
#590000000
0!
0%
#595000000
1!
b11110010 #
1%
b11110010 '
b11110010 +
#600000000
0!
0%
#605000000
1!
1%
b11111 *
b11111 /
#610000000
0!
0%
#615000000
1!
b11110001 #
1%
b11110001 '
b11110001 +
#620000000
0!
0%
#625000000
1!
1%
b00000 *
b0000 ,
b00000 /
b0000 0
#630000000
0!
0%
#635000000
1!
b11110000 #
1%
b11110000 '
b11110000 +
#640000000
0!
0%
#645000000
1!
b0000 $
1%
b0000 (
b0000 )
b00001 *
b0101 ,
b00001 /
b0101 0
#650000000
0!
0%
#655000000
1!
b00000000 #
1%
b00000000 '
b00000000 +
#660000000
0!
0%
#665000000
1!
b0101 $
1%
b0101 (
b0101 )
b00010 *
b0001 ,
b00010 /
b0001 0
#670000000
0!
0%
#675000000
1!
b11111111 #
1%
b11111111 '
b11111111 +
#680000000
0!
0%
#685000000
1!
b0001 $
1%
b0001 (
b0001 )
b00011 *
b0100 ,
b00011 /
b0100 0
#690000000
0!
0%
#695000000
1!
b01111111 #
1%
b01111111 '
b01111111 +
