Project01/prime/prime.vhd
-- Copyright (C) 1991-2012 Altera Corporation
-- Your use of Altera Corporation's design tools, logic functions 
-- and other software and tools, and its AMPP partner logic 
-- functions, and any output files from any of the foregoing 
-- (including device programming or simulation files), and any 
-- associated documentation or information are expressly subject 
-- to the terms and conditions of the Altera Program License 
-- Subscription Agreement, Altera MegaCore Function License 
-- Agreement, or other applicable license agreement, including, 
-- without limitation, that your use is for the sole purpose of 
-- programming logic devices manufactured by Altera and sold by 
-- Altera or its authorized distributors.  Please refer to the 
-- applicable agreement for further details.

-- PROGRAM		"Quartus II 32-bit"
-- VERSION		"Version 12.1 Build 177 11/07/2012 SJ Full Version"
-- CREATED		"Mon Sep 19 14:05:55 2022"

LIBRARY ieee;
USE ieee.std_logic_1164.all; 

LIBRARY work;

ENTITY prime IS 
	PORT
	(
		A :  IN  STD_LOGIC;
		B :  IN  STD_LOGIC;
		C :  IN  STD_LOGIC;
		D :  IN  STD_LOGIC;
		F :  OUT  STD_LOGIC
	);
END prime;

ARCHITECTURE bdf_type OF prime IS 

SIGNAL	SYNTHESIZED_WIRE_0 :  STD_LOGIC;
SIGNAL	SYNTHESIZED_WIRE_1 :  STD_LOGIC;
SIGNAL	SYNTHESIZED_WIRE_2 :  STD_LOGIC;
SIGNAL	SYNTHESIZED_WIRE_3 :  STD_LOGIC;
SIGNAL	SYNTHESIZED_WIRE_4 :  STD_LOGIC;
SIGNAL	SYNTHESIZED_WIRE_5 :  STD_LOGIC;
SIGNAL	SYNTHESIZED_WIRE_6 :  STD_LOGIC;
SIGNAL	SYNTHESIZED_WIRE_7 :  STD_LOGIC;
SIGNAL	SYNTHESIZED_WIRE_8 :  STD_LOGIC;


BEGIN 



SYNTHESIZED_WIRE_5 <= SYNTHESIZED_WIRE_0 AND SYNTHESIZED_WIRE_1 AND C;


SYNTHESIZED_WIRE_8 <= SYNTHESIZED_WIRE_2 AND C AND D;


SYNTHESIZED_WIRE_1 <= NOT(B);



SYNTHESIZED_WIRE_2 <= NOT(A);



SYNTHESIZED_WIRE_3 <= NOT(B);



SYNTHESIZED_WIRE_4 <= NOT(C);



SYNTHESIZED_WIRE_6 <= SYNTHESIZED_WIRE_3 AND C AND D;


SYNTHESIZED_WIRE_7 <= B AND SYNTHESIZED_WIRE_4 AND D;


F <= SYNTHESIZED_WIRE_5 OR SYNTHESIZED_WIRE_6 OR SYNTHESIZED_WIRE_7 OR SYNTHESIZED_WIRE_8;


SYNTHESIZED_WIRE_0 <= NOT(A);



END bdf_type;

Project01/prime/testbench.vhd
-- Stephanie Taylor
-- Fall 2020
-- CS 232 Lab 1
-- Test file for the simple circuit in lab 1

library ieee;
use ieee.std_logic_1164.all;

entity testbench is
end testbench;

architecture one of testbench is

  signal a, b, c, d, f: std_logic;

  component prime
  port( 
    A :  IN  STD_LOGIC;
    B :  IN  STD_LOGIC;
    C :  IN  STD_LOGIC;
    D :  IN  STD_LOGIC;
    F :  OUT  STD_LOGIC
    );
  end component;

begin

A <= '0', '1' after 10 ns, '0' after 20 ns, '1' after 50 ns, '0' after 60 ns, '1' after 110 ns, '0' after 130 ns, '1' after 140 ns, '0' after 180 ns;
B <= '0', '1' after 20 ns, '0' after 30 ns, '1' after 70 ns, '0' after 80 ns, '1' after 100 ns, '0' after 110 ns, '1' after 120 ns, '0' after 140 ns, '1' after 150 ns, '0' after 180 ns;
C <= '0', '1' after 30 ns, '0' after 40 ns, '1' after 90 ns, '0' after 120 ns, '1' after 130 ns, '0' after 150 ns, '1' after 160 ns, '0' after 180 ns;
D <= '0', '1' after 40 ns, '0' after 100 ns, '1' after 130 ns, '0' after 160 ns, '1' after 170 ns, '0' after 180 ns;

T0: prime port map(A, B, C, D, F);

end one;

Project01/prime/testbench.vcd
$date
  Mon Sep 26 21:19:30 2022
$end
$version
  GHDL v0
$end
$timescale
  1 fs
$end
$scope module standard $end
$upscope $end
$scope module std_logic_1164 $end
$upscope $end
$scope module testbench $end
$var reg 1 ! a $end
$var reg 1 " b $end
$var reg 1 # c $end
$var reg 1 $ d $end
$var reg 1 % f $end
$scope module t0 $end
$var reg 1 & a $end
$var reg 1 ' b $end
$var reg 1 ( c $end
$var reg 1 ) d $end
$var reg 1 * f $end
$var reg 1 + synthesized_wire_0 $end
$var reg 1 , synthesized_wire_1 $end
$var reg 1 - synthesized_wire_2 $end
$var reg 1 . synthesized_wire_3 $end
$var reg 1 / synthesized_wire_4 $end
$var reg 1 0 synthesized_wire_5 $end
$var reg 1 1 synthesized_wire_6 $end
$var reg 1 2 synthesized_wire_7 $end
$var reg 1 3 synthesized_wire_8 $end
$upscope $end
$upscope $end
$enddefinitions $end
#0
0!
0"
0#
0$
0%
0&
0'
0(
0)
0*
1+
1,
1-
1.
1/
00
01
02
03
#10000000
1!
1&
0+
0-
#20000000
0!
1"
0&
1'
1+
0,
1-
0.
#30000000
0"
1#
1%
0'
1(
1*
1,
1.
0/
10
#40000000
0#
1$
0%
0(
1)
0*
1/
00
#50000000
1!
1&
0+
0-
#60000000
0!
0&
1+
1-
#70000000
1"
1%
1'
1*
0,
0.
12
#80000000
0"
0%
0'
0*
1,
1.
02
#90000000
1#
1%
1(
1*
0/
10
11
13
#100000000
1"
0$
0%
1'
0)
0*
0,
0.
00
01
03
#110000000
1!
0"
1&
0'
0+
1,
0-
1.
#120000000
1"
0#
1'
0(
0,
0.
1/
#130000000
0!
1#
1$
1%
0&
1(
1)
1*
1+
1-
0/
02
13
#140000000
1!
0"
1&
0'
0+
1,
0-
1.
11
03
#150000000
1"
0#
1%
1'
0(
1*
0,
0.
1/
01
12
#160000000
1#
0$
0%
1(
0)
0*
0/
02
#170000000
1$
1)
#180000000
0!
0"
0#
0$
0&
0'
0(
0)
1+
1,
1-
1.
1/
