Project05/pldrom.vhd
library IEEE;
use IEEE.std_logic_1164.all;
use IEEE.numeric_std.all;

entity pldrom is
	port (
			addr  : in std_logic_vector(4 downto 0);
			data	: out std_logic_vector(9 downto 0)
			);
end pldrom;

architecture one of pldrom is 
begin
  	data <= 
		 "0011100001" when addr = "00000" else -- Move 0001 to ACC high    
		 "0010100000" when addr = "00001" else -- Move 0000 to ACC low
		 "0001000000" when addr = "00010" else -- Move ACC to LR
		 "0100110101" when addr = "00011" else -- Sub 1 from LR
		 "1101100011" when addr = "00100" else -- If LR > 0 branch to 00011
		 "1000000110" when addr = "00101" else -- Else branch to 00110
		 "0001110000" when addr = "00110" else -- Move 1s to LR
		 "0110011100" when addr = "00111" else -- XOR the LR and write it back to the LR (bit inversion)
		 "0100110001" when addr = "01000" else -- Sub 1 from ACC
		 "1101000111" when addr = "01001" else -- If ACC > 0 branch to 00111
		 "1000000000" when addr = "01010" else -- Else branch to 00000
		 "0000000000";                        -- garbage	
end one;

Project05/pld2.vhd
-- Quartus II VHDL Template
-- Four-State Moore State Machine

-- A Moore machine's outputs are dependent only on the current state.
-- The output is written only when the state changes.  (State
-- transitions are synchronous.)

library ieee;
use ieee.std_logic_1164.all;
use ieee.numeric_std.all;

entity pld2 is

	port(
		clk		 : in	std_logic;
		reset	 	 : in	std_logic;
		lights	 : out std_logic_vector(7 downto 0);
		IRView	 : out std_logic_vector(9 downto 0)
	);

end entity;

architecture rtl of pld2 is

	signal IR	: std_logic_vector(9 downto 0);
	signal PC	: unsigned(4 downto 0);
	signal LR	: unsigned(7 downto 0);
	signal ACC	: unsigned(7 downto 0);
	signal SRC	: unsigned(7 downto 0);
	signal ROMvalue	: std_logic_vector(9 downto 0);

	-- Build an enumerated type for the state machine
	type state_type is (sFetch, sExecute1, sExecute2);

	-- Register to hold the current state
	signal state   : state_type;
		
component pldrom
    port (
			addr  : in std_logic_vector(4 downto 0);
			data	: out std_logic_vector(9 downto 0)
	 );
end component;

begin

	pldrom1 : pldrom
	port map(
		addr => std_logic_vector(PC),
		data => ROMvalue
	);

	-- Logic to advance to the next state
	process (clk, reset)
	begin
		if reset = '0' then
			state <= sFetch;
			PC <= (others=>'0');
			IR <= (others=>'0');
			LR <= (others=>'0');
		elsif (rising_edge(clk)) then
			case state is
				when sFetch=>
					IR <= ROMvalue;
					PC <= PC + 1;
					state <= sExecute1;
				when sExecute1=>
					case IR(9 downto 8) is
						when "00" =>
							case IR(5 downto 4) is
								when "00" =>
									SRC <= ACC;
								when "01" =>
									SRC <= LR;
								when "10" =>
									SRC <= unsigned(IR(3) & IR(3) & IR(3) & IR(3) & IR(3 downto 0));
								when others =>
									SRC <= (others=>'1');
							end case;
						when "01"=>
							case IR(4 downto 3) is
								when "00" =>
									SRC <= ACC;
								when "01" =>
									SRC <= LR;
								when "10" =>
									SRC <= unsigned(IR(1) & IR(1) & IR(1) & IR(1) & IR(1) & IR(1) & IR(1 downto 0));
								when others =>
									SRC <= (others=>'1');
							end case;
						when "10" =>
							PC <= unsigned(IR(4 downto 0));
						when others =>
							case IR(7 downto 5) is
								when "000" =>
									if ACC = 0 then
										PC <= unsigned(IR(4 downto 0));
									end if;
								when "001" =>
									if LR = 0 then
										PC <= unsigned(IR(4 downto 0));
									end if;
								when "010" =>
									if ACC > 0 then
										PC <= unsigned(IR(4 downto 0));
									end if;
								when "011" =>
									if LR > 0 then
										PC <= unsigned(IR(4 downto 0));
									end if;
								when "100" =>
									if ACC < 1023 then
										PC <= unsigned(IR(4 downto 0));
									end if;
								when others =>
									if LR > 1023 then
										PC <= unsigned(IR(4 downto 0));
									end if;
							end case;
					end case;
					state <= sExecute2;
					
				when sExecute2=>
					case IR(9 downto 8) is
						when "00" =>
							case IR(7 downto 6) is
								when "00" =>
									ACC <= SRC;									
								when "01" =>
									LR <= SRC;									
								when "10" =>
									ACC(3 downto 0) <= SRC(3 downto 0);									
								when others =>
									ACC(7 downto 4) <= SRC(3 downto 0);									
							end case;
						when "01" =>
							case IR(2) is
								when '0' =>
									case IR(7 downto 5) is
										when "000" =>
											ACC <= ACC + SRC;											
										when "001" =>
											ACC <= ACC - SRC;											
										when "010" =>
											ACC <= SRC(6 downto 0) & '0';											
										when "011" =>
											ACC <= SRC(7) & SRC(7 downto 1);											
										when "100" =>
											ACC <= ACC xor SRC;											
										when "101" =>
											ACC <= ACC and SRC;											
										when "110" =>
											ACC <= SRC(6 downto 0) & SRC(7);											
										when others =>
											ACC <= SRC(0) & SRC(7 downto 1);											
									end case;
								when '1' =>
									case IR(7 downto 5) is
										when "000" =>
											LR <= LR + SRC;											
										when "001" =>
											LR <= LR - SRC;											
										when "010" =>
											LR <= SRC(6 downto 0) & '0';											
										when "011" =>
											LR <= SRC(7) & SRC(7 downto 1);												
										when "100" =>
											LR <= LR xor SRC;											
										when "101" =>
											LR <= LR and SRC;										
										when "110" =>
											LR <= SRC(6 downto 0) & SRC(7);												
										when others =>
											LR <= SRC(0) & SRC(7 downto 1);											
									end case;
								when others => 
							end case;
						when others =>
					end case;
					state <= sFetch;
					
				when others =>
			end case;
		end if;
	end process;				

lights <= std_logic_vector(LR);
IRView <= IR;
	
end rtl;

Project05/pldbench.vhd
-- Bruce A. Maxwell
-- Spring 2013
-- CS 232
--
-- test program for the lights circuit
--

library ieee;
use ieee.std_logic_1164.all;
use ieee.numeric_std.all;

entity pldbench is
end entity;

architecture test of pldbench is
  constant num_cycles : integer := 500;

  -- this circuit just needs a clock and a reset
  signal clk : std_logic := '1';
  signal reset : std_logic;

  -- lights component
  component pld2
    port( clk, reset : in std_logic;
          lights   : out std_logic_vector(7 downto 0);
          IRView     : out std_logic_vector(9 downto 0) );
  end component;

  -- output signals
  signal lightsig : std_logic_vector(7 downto 0);
  signal irview : std_logic_vector(9 downto 0);

begin

  -- start off with a short reset
  reset <= '0', '1' after 5 ns;

  -- create a clock
  process begin
    for i in 1 to num_cycles loop
      clk <= not clk;
      wait for 5 ns;
      clk <= not clk;
      wait for 5 ns;
    end loop;
    wait;
  end process;

  -- port map the circuit
  L0: pld2 port map( clk, reset, lightsig, irview );

end test;

Project05/pldbench.vcd
$date
  Sun Oct 30 17:23:46 2022
$end
$version
  GHDL v0
$end
$timescale
  1 fs
$end
$scope module standard $end
$upscope $end
$scope module std_logic_1164 $end
$upscope $end
$scope module numeric_std $end
$upscope $end
$scope module pldbench $end
$var reg 1 ! clk $end
$var reg 1 " reset $end
$var reg 8 # lightsig[7:0] $end
$var reg 10 $ irview[9:0] $end
$scope module l0 $end
$var reg 1 % clk $end
$var reg 1 & reset $end
$var reg 8 ' lights[7:0] $end
$var reg 10 ( irview[9:0] $end
$var reg 10 ) ir[9:0] $end
$var reg 5 * pc[4:0] $end
$var reg 8 + lr[7:0] $end
$var reg 8 , acc[7:0] $end
$var reg 8 - src[7:0] $end
$var reg 10 . romvalue[9:0] $end
$comment state is not handled $end
$scope module pldrom1 $end
$var reg 5 / addr[4:0] $end
$var reg 10 0 data[9:0] $end
$upscope $end
$upscope $end
$upscope $end
$enddefinitions $end
#0
0!
0"
b00000000 #
b0000000000 $
0%
0&
b00000000 '
b0000000000 (
b0000000000 )
b00000 *
b00000000 +
bUUUUUUUU ,
bUUUUUUUU -
b0011100001 .
b00000 /
b0011100001 0
#5000000
1!
1"
b0011100001 $
1%
1&
b0011100001 (
b0011100001 )
b00001 *
b0010100000 .
b00001 /
b0010100000 0
#10000000
0!
0%
#15000000
1!
1%
b00000001 -
#20000000
0!
0%
#25000000
1!
1%
b0001UUUU ,
#30000000
0!
0%
#35000000
1!
b0010100000 $
1%
b0010100000 (
b0010100000 )
b00010 *
b0001000000 .
b00010 /
b0001000000 0
#40000000
0!
0%
#45000000
1!
1%
b00000000 -
#50000000
0!
0%
#55000000
1!
1%
b00010000 ,
#60000000
0!
0%
#65000000
1!
b0001000000 $
1%
b0001000000 (
b0001000000 )
b00011 *
b0100110101 .
b00011 /
b0100110101 0
#70000000
0!
0%
#75000000
1!
1%
b00010000 -
#80000000
0!
0%
#85000000
1!
b00010000 #
1%
b00010000 '
b00010000 +
#90000000
0!
0%
#95000000
1!
b0100110101 $
1%
b0100110101 (
b0100110101 )
b00100 *
b1101100011 .
b00100 /
b1101100011 0
#100000000
0!
0%
#105000000
1!
1%
b00000001 -
#110000000
0!
0%
#115000000
1!
b00001111 #
1%
b00001111 '
b00001111 +
#120000000
0!
0%
#125000000
1!
b1101100011 $
1%
b1101100011 (
b1101100011 )
b00101 *
b1000000110 .
b00101 /
b1000000110 0
#130000000
0!
0%
#135000000
1!
1%
b00011 *
b0100110101 .
b00011 /
b0100110101 0
#140000000
0!
0%
#145000000
1!
1%
#150000000
0!
0%
#155000000
1!
b0100110101 $
1%
b0100110101 (
b0100110101 )
b00100 *
b1101100011 .
b00100 /
b1101100011 0
#160000000
0!
0%
#165000000
1!
1%
#170000000
0!
0%
#175000000
1!
b00001110 #
1%
b00001110 '
b00001110 +
#180000000
0!
0%
#185000000
1!
b1101100011 $
1%
b1101100011 (
b1101100011 )
b00101 *
b1000000110 .
b00101 /
b1000000110 0
#190000000
0!
0%
#195000000
1!
1%
b00011 *
b0100110101 .
b00011 /
b0100110101 0
#200000000
0!
0%
#205000000
1!
1%
#210000000
0!
0%
#215000000
1!
b0100110101 $
1%
b0100110101 (
b0100110101 )
b00100 *
b1101100011 .
b00100 /
b1101100011 0
#220000000
0!
0%
#225000000
1!
1%
#230000000
0!
0%
#235000000
1!
b00001101 #
1%
b00001101 '
b00001101 +
#240000000
0!
0%
#245000000
1!
b1101100011 $
1%
b1101100011 (
b1101100011 )
b00101 *
b1000000110 .
b00101 /
b1000000110 0
#250000000
0!
0%
#255000000
1!
1%
b00011 *
b0100110101 .
b00011 /
b0100110101 0
#260000000
0!
0%
#265000000
1!
1%
#270000000
0!
0%
#275000000
1!
b0100110101 $
1%
b0100110101 (
b0100110101 )
b00100 *
b1101100011 .
b00100 /
b1101100011 0
#280000000
0!
0%
#285000000
1!
1%
#290000000
0!
0%
#295000000
1!
b00001100 #
1%
b00001100 '
b00001100 +
#300000000
0!
0%
#305000000
1!
b1101100011 $
1%
b1101100011 (
b1101100011 )
b00101 *
b1000000110 .
b00101 /
b1000000110 0
#310000000
0!
0%
#315000000
1!
1%
b00011 *
b0100110101 .
b00011 /
b0100110101 0
#320000000
0!
0%
#325000000
1!
1%
#330000000
0!
0%
#335000000
1!
b0100110101 $
1%
b0100110101 (
b0100110101 )
b00100 *
b1101100011 .
b00100 /
b1101100011 0
#340000000
0!
0%
#345000000
1!
1%
#350000000
0!
0%
#355000000
1!
b00001011 #
1%
b00001011 '
b00001011 +
#360000000
0!
0%
#365000000
1!
b1101100011 $
1%
b1101100011 (
b1101100011 )
b00101 *
b1000000110 .
b00101 /
b1000000110 0
#370000000
0!
0%
#375000000
1!
1%
b00011 *
b0100110101 .
b00011 /
b0100110101 0
#380000000
0!
0%
#385000000
1!
1%
#390000000
0!
0%
#395000000
1!
b0100110101 $
1%
b0100110101 (
b0100110101 )
b00100 *
b1101100011 .
b00100 /
b1101100011 0
#400000000
0!
0%
#405000000
1!
1%
#410000000
0!
0%
#415000000
1!
b00001010 #
1%
b00001010 '
b00001010 +
#420000000
0!
0%
#425000000
1!
b1101100011 $
1%
b1101100011 (
b1101100011 )
b00101 *
b1000000110 .
b00101 /
b1000000110 0
#430000000
0!
0%
#435000000
1!
1%
b00011 *
b0100110101 .
b00011 /
b0100110101 0
#440000000
0!
0%
#445000000
1!
1%
#450000000
0!
0%
#455000000
1!
b0100110101 $
1%
b0100110101 (
b0100110101 )
b00100 *
b1101100011 .
b00100 /
b1101100011 0
#460000000
0!
0%
#465000000
1!
1%
#470000000
0!
0%
#475000000
1!
b00001001 #
1%
b00001001 '
b00001001 +
#480000000
0!
0%
#485000000
1!
b1101100011 $
1%
b1101100011 (
b1101100011 )
b00101 *
b1000000110 .
b00101 /
b1000000110 0
#490000000
0!
0%
#495000000
1!
1%
b00011 *
b0100110101 .
b00011 /
b0100110101 0
#500000000
0!
0%
#505000000
1!
1%
#510000000
0!
0%
#515000000
1!
b0100110101 $
1%
b0100110101 (
b0100110101 )
b00100 *
b1101100011 .
b00100 /
b1101100011 0
#520000000
0!
0%
#525000000
1!
1%
#530000000
0!
0%
#535000000
1!
b00001000 #
1%
b00001000 '
b00001000 +
#540000000
0!
0%
#545000000
1!
b1101100011 $
1%
b1101100011 (
b1101100011 )
b00101 *
b1000000110 .
b00101 /
b1000000110 0
#550000000
0!
0%
#555000000
1!
1%
b00011 *
b0100110101 .
b00011 /
b0100110101 0
#560000000
0!
0%
#565000000
1!
1%
#570000000
0!
0%
#575000000
1!
b0100110101 $
1%
b0100110101 (
b0100110101 )
b00100 *
b1101100011 .
b00100 /
b1101100011 0
#580000000
0!
0%
#585000000
1!
1%
#590000000
0!
0%
#595000000
1!
b00000111 #
1%
b00000111 '
b00000111 +
#600000000
0!
0%
#605000000
1!
b1101100011 $
1%
b1101100011 (
b1101100011 )
b00101 *
b1000000110 .
b00101 /
b1000000110 0
#610000000
0!
0%
#615000000
1!
1%
b00011 *
b0100110101 .
b00011 /
b0100110101 0
#620000000
0!
0%
#625000000
1!
1%
#630000000
0!
0%
#635000000
1!
b0100110101 $
1%
b0100110101 (
b0100110101 )
b00100 *
b1101100011 .
b00100 /
b1101100011 0
#640000000
0!
0%
#645000000
1!
1%
#650000000
0!
0%
#655000000
1!
b00000110 #
1%
b00000110 '
b00000110 +
#660000000
0!
0%
#665000000
1!
b1101100011 $
1%
b1101100011 (
b1101100011 )
b00101 *
b1000000110 .
b00101 /
b1000000110 0
#670000000
0!
0%
#675000000
1!
1%
b00011 *
b0100110101 .
b00011 /
b0100110101 0
#680000000
0!
0%
#685000000
1!
1%
#690000000
0!
0%
#695000000
1!
b0100110101 $
1%
b0100110101 (
b0100110101 )
b00100 *
b1101100011 .
b00100 /
b1101100011 0
#700000000
0!
0%
#705000000
1!
1%
#710000000
0!
0%
#715000000
1!
b00000101 #
1%
b00000101 '
b00000101 +
#720000000
0!
0%
#725000000
1!
b1101100011 $
1%
b1101100011 (
b1101100011 )
b00101 *
b1000000110 .
b00101 /
b1000000110 0
#730000000
0!
0%
#735000000
1!
1%
b00011 *
b0100110101 .
b00011 /
b0100110101 0
#740000000
0!
0%
#745000000
1!
1%
#750000000
0!
0%
#755000000
1!
b0100110101 $
1%
b0100110101 (
b0100110101 )
b00100 *
b1101100011 .
b00100 /
b1101100011 0
#760000000
0!
0%
#765000000
1!
1%
#770000000
0!
0%
#775000000
1!
b00000100 #
1%
b00000100 '
b00000100 +
#780000000
0!
0%
#785000000
1!
b1101100011 $
1%
b1101100011 (
b1101100011 )
b00101 *
b1000000110 .
b00101 /
b1000000110 0
#790000000
0!
0%
#795000000
1!
1%
b00011 *
b0100110101 .
b00011 /
b0100110101 0
#800000000
0!
0%
#805000000
1!
1%
#810000000
0!
0%
#815000000
1!
b0100110101 $
1%
b0100110101 (
b0100110101 )
b00100 *
b1101100011 .
b00100 /
b1101100011 0
#820000000
0!
0%
#825000000
1!
1%
#830000000
0!
0%
#835000000
1!
b00000011 #
1%
b00000011 '
b00000011 +
#840000000
0!
0%
#845000000
1!
b1101100011 $
1%
b1101100011 (
b1101100011 )
b00101 *
b1000000110 .
b00101 /
b1000000110 0
#850000000
0!
0%
#855000000
1!
1%
b00011 *
b0100110101 .
b00011 /
b0100110101 0
#860000000
0!
0%
#865000000
1!
1%
#870000000
0!
0%
#875000000
1!
b0100110101 $
1%
b0100110101 (
b0100110101 )
b00100 *
b1101100011 .
b00100 /
b1101100011 0
#880000000
0!
0%
#885000000
1!
1%
#890000000
0!
0%
#895000000
1!
b00000010 #
1%
b00000010 '
b00000010 +
#900000000
0!
0%
#905000000
1!
b1101100011 $
1%
b1101100011 (
b1101100011 )
b00101 *
b1000000110 .
b00101 /
b1000000110 0
#910000000
0!
0%
#915000000
1!
1%
b00011 *
b0100110101 .
b00011 /
b0100110101 0
#920000000
0!
0%
#925000000
1!
1%
#930000000
0!
0%
#935000000
1!
b0100110101 $
1%
b0100110101 (
b0100110101 )
b00100 *
b1101100011 .
b00100 /
b1101100011 0
#940000000
0!
0%
#945000000
1!
1%
#950000000
0!
0%
#955000000
1!
b00000001 #
1%
b00000001 '
b00000001 +
#960000000
0!
0%
#965000000
1!
b1101100011 $
1%
b1101100011 (
b1101100011 )
b00101 *
b1000000110 .
b00101 /
b1000000110 0
#970000000
0!
0%
#975000000
1!
1%
b00011 *
b0100110101 .
b00011 /
b0100110101 0
#980000000
0!
0%
#985000000
1!
1%
#990000000
0!
0%
#995000000
1!
b0100110101 $
1%
b0100110101 (
b0100110101 )
b00100 *
b1101100011 .
b00100 /
b1101100011 0
#1000000000
0!
0%
#1005000000
1!
1%
#1010000000
0!
0%
#1015000000
1!
b00000000 #
1%
b00000000 '
b00000000 +
#1020000000
0!
0%
#1025000000
1!
b1101100011 $
1%
b1101100011 (
b1101100011 )
b00101 *
b1000000110 .
b00101 /
b1000000110 0
#1030000000
0!
0%
#1035000000
1!
1%
#1040000000
0!
0%
#1045000000
1!
1%
#1050000000
0!
0%
#1055000000
1!
b1000000110 $
1%
b1000000110 (
b1000000110 )
b00110 *
b0001110000 .
b00110 /
b0001110000 0
#1060000000
0!
0%
#1065000000
1!
1%
#1070000000
0!
0%
#1075000000
1!
1%
#1080000000
0!
0%
#1085000000
1!
b0001110000 $
1%
b0001110000 (
b0001110000 )
b00111 *
b0110011100 .
b00111 /
b0110011100 0
#1090000000
0!
0%
#1095000000
1!
1%
b11111111 -
#1100000000
0!
0%
#1105000000
1!
b11111111 #
1%
b11111111 '
b11111111 +
#1110000000
0!
0%
#1115000000
1!
b0110011100 $
1%
b0110011100 (
b0110011100 )
b01000 *
b0100110001 .
b01000 /
b0100110001 0
#1120000000
0!
0%
#1125000000
1!
1%
#1130000000
0!
0%
#1135000000
1!
b00000000 #
1%
b00000000 '
b00000000 +
#1140000000
0!
0%
#1145000000
1!
b0100110001 $
1%
b0100110001 (
b0100110001 )
b01001 *
b1101000111 .
b01001 /
b1101000111 0
#1150000000
0!
0%
#1155000000
1!
1%
b00000001 -
#1160000000
0!
0%
#1165000000
1!
1%
b00001111 ,
#1170000000
0!
0%
#1175000000
1!
b1101000111 $
1%
b1101000111 (
b1101000111 )
b01010 *
b1000000000 .
b01010 /
b1000000000 0
#1180000000
0!
0%
#1185000000
1!
1%
b00111 *
b0110011100 .
b00111 /
b0110011100 0
#1190000000
0!
0%
#1195000000
1!
1%
#1200000000
0!
0%
#1205000000
1!
b0110011100 $
1%
b0110011100 (
b0110011100 )
b01000 *
b0100110001 .
b01000 /
b0100110001 0
#1210000000
0!
0%
#1215000000
1!
1%
b11111111 -
#1220000000
0!
0%
#1225000000
1!
b11111111 #
1%
b11111111 '
b11111111 +
#1230000000
0!
0%
#1235000000
1!
b0100110001 $
1%
b0100110001 (
b0100110001 )
b01001 *
b1101000111 .
b01001 /
b1101000111 0
#1240000000
0!
0%
#1245000000
1!
1%
b00000001 -
#1250000000
0!
0%
#1255000000
1!
1%
b00001110 ,
#1260000000
0!
0%
#1265000000
1!
b1101000111 $
1%
b1101000111 (
b1101000111 )
b01010 *
b1000000000 .
b01010 /
b1000000000 0
#1270000000
0!
0%
#1275000000
1!
1%
b00111 *
b0110011100 .
b00111 /
b0110011100 0
#1280000000
0!
0%
#1285000000
1!
1%
#1290000000
0!
0%
#1295000000
1!
b0110011100 $
1%
b0110011100 (
b0110011100 )
b01000 *
b0100110001 .
b01000 /
b0100110001 0
#1300000000
0!
0%
#1305000000
1!
1%
b11111111 -
#1310000000
0!
0%
#1315000000
1!
b00000000 #
1%
b00000000 '
b00000000 +
#1320000000
0!
0%
#1325000000
1!
b0100110001 $
1%
b0100110001 (
b0100110001 )
b01001 *
b1101000111 .
b01001 /
b1101000111 0
#1330000000
0!
0%
#1335000000
1!
1%
b00000001 -
#1340000000
0!
0%
#1345000000
1!
1%
b00001101 ,
#1350000000
0!
0%
#1355000000
1!
b1101000111 $
1%
b1101000111 (
b1101000111 )
b01010 *
b1000000000 .
b01010 /
b1000000000 0
#1360000000
0!
0%
#1365000000
1!
1%
b00111 *
b0110011100 .
b00111 /
b0110011100 0
#1370000000
0!
0%
#1375000000
1!
1%
#1380000000
0!
0%
#1385000000
1!
b0110011100 $
1%
b0110011100 (
b0110011100 )
b01000 *
b0100110001 .
b01000 /
b0100110001 0
#1390000000
0!
0%
#1395000000
1!
1%
b11111111 -
#1400000000
0!
0%
#1405000000
1!
b11111111 #
1%
b11111111 '
b11111111 +
#1410000000
0!
0%
#1415000000
1!
b0100110001 $
1%
b0100110001 (
b0100110001 )
b01001 *
b1101000111 .
b01001 /
b1101000111 0
#1420000000
0!
0%
#1425000000
1!
1%
b00000001 -
#1430000000
0!
0%
#1435000000
1!
1%
b00001100 ,
#1440000000
0!
0%
#1445000000
1!
b1101000111 $
1%
b1101000111 (
b1101000111 )
b01010 *
b1000000000 .
b01010 /
b1000000000 0
#1450000000
0!
0%
#1455000000
1!
1%
b00111 *
b0110011100 .
b00111 /
b0110011100 0
#1460000000
0!
0%
#1465000000
1!
1%
#1470000000
0!
0%
#1475000000
1!
b0110011100 $
1%
b0110011100 (
b0110011100 )
b01000 *
b0100110001 .
b01000 /
b0100110001 0
#1480000000
0!
0%
#1485000000
1!
1%
b11111111 -
#1490000000
0!
0%
#1495000000
1!
b00000000 #
1%
b00000000 '
b00000000 +
#1500000000
0!
0%
#1505000000
1!
b0100110001 $
1%
b0100110001 (
b0100110001 )
b01001 *
b1101000111 .
b01001 /
b1101000111 0
#1510000000
0!
0%
#1515000000
1!
1%
b00000001 -
#1520000000
0!
0%
#1525000000
1!
1%
b00001011 ,
#1530000000
0!
0%
#1535000000
1!
b1101000111 $
1%
b1101000111 (
b1101000111 )
b01010 *
b1000000000 .
b01010 /
b1000000000 0
#1540000000
0!
0%
#1545000000
1!
1%
b00111 *
b0110011100 .
b00111 /
b0110011100 0
#1550000000
0!
0%
#1555000000
1!
1%
#1560000000
0!
0%
#1565000000
1!
b0110011100 $
1%
b0110011100 (
b0110011100 )
b01000 *
b0100110001 .
b01000 /
b0100110001 0
#1570000000
0!
0%
#1575000000
1!
1%
b11111111 -
#1580000000
0!
0%
#1585000000
1!
b11111111 #
1%
b11111111 '
b11111111 +
#1590000000
0!
0%
#1595000000
1!
b0100110001 $
1%
b0100110001 (
b0100110001 )
b01001 *
b1101000111 .
b01001 /
b1101000111 0
#1600000000
0!
0%
#1605000000
1!
1%
b00000001 -
#1610000000
0!
0%
#1615000000
1!
1%
b00001010 ,
#1620000000
0!
0%
#1625000000
1!
b1101000111 $
1%
b1101000111 (
b1101000111 )
b01010 *
b1000000000 .
b01010 /
b1000000000 0
#1630000000
0!
0%
#1635000000
1!
1%
b00111 *
b0110011100 .
b00111 /
b0110011100 0
#1640000000
0!
0%
#1645000000
1!
1%
#1650000000
0!
0%
#1655000000
1!
b0110011100 $
1%
b0110011100 (
b0110011100 )
b01000 *
b0100110001 .
b01000 /
b0100110001 0
#1660000000
0!
0%
#1665000000
1!
1%
b11111111 -
#1670000000
0!
0%
#1675000000
1!
b00000000 #
1%
b00000000 '
b00000000 +
#1680000000
0!
0%
#1685000000
1!
b0100110001 $
1%
b0100110001 (
b0100110001 )
b01001 *
b1101000111 .
b01001 /
b1101000111 0
#1690000000
0!
0%
#1695000000
1!
1%
b00000001 -
#1700000000
0!
0%
#1705000000
1!
1%
b00001001 ,
#1710000000
0!
0%
#1715000000
1!
b1101000111 $
1%
b1101000111 (
b1101000111 )
b01010 *
b1000000000 .
b01010 /
b1000000000 0
#1720000000
0!
0%
#1725000000
1!
1%
b00111 *
b0110011100 .
b00111 /
b0110011100 0
#1730000000
0!
0%
#1735000000
1!
1%
#1740000000
0!
0%
#1745000000
1!
b0110011100 $
1%
b0110011100 (
b0110011100 )
b01000 *
b0100110001 .
b01000 /
b0100110001 0
#1750000000
0!
0%
#1755000000
1!
1%
b11111111 -
#1760000000
0!
0%
#1765000000
1!
b11111111 #
1%
b11111111 '
b11111111 +
#1770000000
0!
0%
#1775000000
1!
b0100110001 $
1%
b0100110001 (
b0100110001 )
b01001 *
b1101000111 .
b01001 /
b1101000111 0
#1780000000
0!
0%
#1785000000
1!
1%
b00000001 -
#1790000000
0!
0%
#1795000000
1!
1%
b00001000 ,
#1800000000
0!
0%
#1805000000
1!
b1101000111 $
1%
b1101000111 (
b1101000111 )
b01010 *
b1000000000 .
b01010 /
b1000000000 0
#1810000000
0!
0%
#1815000000
1!
1%
b00111 *
b0110011100 .
b00111 /
b0110011100 0
#1820000000
0!
0%
#1825000000
1!
1%
#1830000000
0!
0%
#1835000000
1!
b0110011100 $
1%
b0110011100 (
b0110011100 )
b01000 *
b0100110001 .
b01000 /
b0100110001 0
#1840000000
0!
0%
#1845000000
1!
1%
b11111111 -
#1850000000
0!
0%
#1855000000
1!
b00000000 #
1%
b00000000 '
b00000000 +
#1860000000
0!
0%
#1865000000
1!
b0100110001 $
1%
b0100110001 (
b0100110001 )
b01001 *
b1101000111 .
b01001 /
b1101000111 0
#1870000000
0!
0%
#1875000000
1!
1%
b00000001 -
#1880000000
0!
0%
#1885000000
1!
1%
b00000111 ,
#1890000000
0!
0%
#1895000000
1!
b1101000111 $
1%
b1101000111 (
b1101000111 )
b01010 *
b1000000000 .
b01010 /
b1000000000 0
#1900000000
0!
0%
#1905000000
1!
1%
b00111 *
b0110011100 .
b00111 /
b0110011100 0
#1910000000
0!
0%
#1915000000
1!
1%
#1920000000
0!
0%
#1925000000
1!
b0110011100 $
1%
b0110011100 (
b0110011100 )
b01000 *
b0100110001 .
b01000 /
b0100110001 0
#1930000000
0!
0%
#1935000000
1!
1%
b11111111 -
#1940000000
0!
0%
#1945000000
1!
b11111111 #
1%
b11111111 '
b11111111 +
#1950000000
0!
0%
#1955000000
1!
b0100110001 $
1%
b0100110001 (
b0100110001 )
b01001 *
b1101000111 .
b01001 /
b1101000111 0
#1960000000
0!
0%
#1965000000
1!
1%
b00000001 -
#1970000000
0!
0%
#1975000000
1!
1%
b00000110 ,
#1980000000
0!
0%
#1985000000
1!
b1101000111 $
1%
b1101000111 (
b1101000111 )
b01010 *
b1000000000 .
b01010 /
b1000000000 0
#1990000000
0!
0%
#1995000000
1!
1%
b00111 *
b0110011100 .
b00111 /
b0110011100 0
#2000000000
0!
0%
#2005000000
1!
1%
#2010000000
0!
0%
#2015000000
1!
b0110011100 $
1%
b0110011100 (
b0110011100 )
b01000 *
b0100110001 .
b01000 /
b0100110001 0
#2020000000
0!
0%
#2025000000
1!
1%
b11111111 -
#2030000000
0!
0%
#2035000000
1!
b00000000 #
1%
b00000000 '
b00000000 +
#2040000000
0!
0%
#2045000000
1!
b0100110001 $
1%
b0100110001 (
b0100110001 )
b01001 *
b1101000111 .
b01001 /
b1101000111 0
#2050000000
0!
0%
#2055000000
1!
1%
b00000001 -
#2060000000
0!
0%
#2065000000
1!
1%
b00000101 ,
#2070000000
0!
0%
#2075000000
1!
b1101000111 $
1%
b1101000111 (
b1101000111 )
b01010 *
b1000000000 .
b01010 /
b1000000000 0
#2080000000
0!
0%
#2085000000
1!
1%
b00111 *
b0110011100 .
b00111 /
b0110011100 0
#2090000000
0!
0%
#2095000000
1!
1%
#2100000000
0!
0%
#2105000000
1!
b0110011100 $
1%
b0110011100 (
b0110011100 )
b01000 *
b0100110001 .
b01000 /
b0100110001 0
#2110000000
0!
0%
#2115000000
1!
1%
b11111111 -
#2120000000
0!
0%
#2125000000
1!
b11111111 #
1%
b11111111 '
b11111111 +
#2130000000
0!
0%
#2135000000
1!
b0100110001 $
1%
b0100110001 (
b0100110001 )
b01001 *
b1101000111 .
b01001 /
b1101000111 0
#2140000000
0!
0%
#2145000000
1!
1%
b00000001 -
#2150000000
0!
0%
#2155000000
1!
1%
b00000100 ,
#2160000000
0!
0%
#2165000000
1!
b1101000111 $
1%
b1101000111 (
b1101000111 )
b01010 *
b1000000000 .
b01010 /
b1000000000 0
#2170000000
0!
0%
#2175000000
1!
1%
b00111 *
b0110011100 .
b00111 /
b0110011100 0
#2180000000
0!
0%
#2185000000
1!
1%
#2190000000
0!
0%
#2195000000
1!
b0110011100 $
1%
b0110011100 (
b0110011100 )
b01000 *
b0100110001 .
b01000 /
b0100110001 0
#2200000000
0!
0%
#2205000000
1!
1%
b11111111 -
#2210000000
0!
0%
#2215000000
1!
b00000000 #
1%
b00000000 '
b00000000 +
#2220000000
0!
0%
#2225000000
1!
b0100110001 $
1%
b0100110001 (
b0100110001 )
b01001 *
b1101000111 .
b01001 /
b1101000111 0
#2230000000
0!
0%
#2235000000
1!
1%
b00000001 -
#2240000000
0!
0%
#2245000000
1!
1%
b00000011 ,
#2250000000
0!
0%
#2255000000
1!
b1101000111 $
1%
b1101000111 (
b1101000111 )
b01010 *
b1000000000 .
b01010 /
b1000000000 0
#2260000000
0!
0%
#2265000000
1!
1%
b00111 *
b0110011100 .
b00111 /
b0110011100 0
#2270000000
0!
0%
#2275000000
1!
1%
#2280000000
0!
0%
#2285000000
1!
b0110011100 $
1%
b0110011100 (
b0110011100 )
b01000 *
b0100110001 .
b01000 /
b0100110001 0
#2290000000
0!
0%
#2295000000
1!
1%
b11111111 -
#2300000000
0!
0%
#2305000000
1!
b11111111 #
1%
b11111111 '
b11111111 +
#2310000000
0!
0%
#2315000000
1!
b0100110001 $
1%
b0100110001 (
b0100110001 )
b01001 *
b1101000111 .
b01001 /
b1101000111 0
#2320000000
0!
0%
#2325000000
1!
1%
b00000001 -
#2330000000
0!
0%
#2335000000
1!
1%
b00000010 ,
#2340000000
0!
0%
