Project02/counter8.vhd
-- Quartus II VHDL Template
-- Binary Counter
-- modified by Taylor F20

library ieee;
use ieee.std_logic_1164.all;
use ieee.numeric_std.all;

entity counter8 is

  port
    (
      clk         : in std_logic;
      reset	  : in std_logic;
      enable	  : in std_logic;
      q  	      : out unsigned(7 downto 0)
      );

end entity;

architecture rtl of counter8 is
    signal cnt : unsigned(7 downto 0);
begin

  process (clk)
  begin
    if reset = '1' then
      -- Reset the counter to 0
      cnt <= "00000000";
    elsif (rising_edge(clk)) then
      if enable = '1' then
        -- Increment the counter if counting is enabled			   
        cnt <= cnt + 1;
      end if;
    end if;
  end process;
  
  q <= cnt;

end rtl;

Project03/hexdisplay.vhd
library IEEE;
use IEEE.std_logic_1164.all;
use IEEE.numeric_std.all;

entity hexdisplay is
	port (
			A	 :	in  unsigned(3 downto 0);
			hex : out unsigned(6 downto 0)
			);
end hexdisplay;

architecture test of hexdisplay is			
begin
		hex	<= 
			"1000000" when A = "0000" else
			"1111001" when A = "0001" else
			"0100100" when A = "0010" else
			"0110000" when A = "0011" else
			"0011001" when A = "0100" else
			"0010010" when A = "0101" else
			"0000010" when A = "0110" else
			"1111000" when A = "0111" else
			"0000000" when A = "1000" else
			"0011000" when A = "1001" else
			"0001000" when A = "1010" else
			"0000011" when A = "1011" else
			"1000110" when A = "1100" else
			"0100001" when A = "1101" else
			"0000110" when A = "1110" else
			"0001110" when A = "1111";		

end test;

Project02/hexbench2.vhd
-- Stephanie Taylor
-- Fall 2020
-- CS 232 Testbench for 2 7-segment displays

library ieee;
use ieee.std_logic_1164.all;
use ieee.numeric_std.all;

entity hexbench2 is
end hexbench2;

architecture one of hexbench2 is

  constant num_cycles : integer := 255;  -- run for 40 clock cycles

  -- this circuit needs a clock, enable, and a reset
  -- for the counter
  signal clk      : std_logic := '1';
  signal reset, enable: std_logic;
  -- signal for count
  signal num : unsigned(7 downto 0);
  -- signals for each hex display
  signal disp0 : unsigned(6 downto 0);
  signal disp1 : unsigned(6 downto 0);

  component hexdisplay
  port(
    A :  IN UNSIGNED(3 downto 0);
    hex: OUT UNSIGNED(6 downto 0)
    );
  end component;
  
  component counter8 is
  port
    (
      clk         : in std_logic;
      reset	  : in std_logic;
      enable	  : in std_logic;
      q  	      : out unsigned(7 downto 0)
      );
end component;

begin

  -- start off with a short reset
  reset <= '1', '0' after 5 ns;

  enable <= '1';

  -- create a clock
  process begin
    for i in 1 to num_cycles loop
      clk <= not clk;
      wait for 5 ns;
      clk <= not clk;
      wait for 5 ns;
    end loop;
    wait;
  end process;

T0: hexdisplay port map(num(3 downto 0),disp0);
T1: hexdisplay port map(num(7 downto 4),disp1);
T2: counter8 port map(clk,reset,enable,num);

end one;

Project02/hexbench2.vcd
$date
  Sun Oct  2 13:37:46 2022
$end
$version
  GHDL v0
$end
$timescale
  1 fs
$end
$scope module standard $end
$upscope $end
$scope module std_logic_1164 $end
$upscope $end
$scope module numeric_std $end
$upscope $end
$scope module hexbench2 $end
$var reg 1 ! clk $end
$var reg 1 " reset $end
$var reg 1 # enable $end
$var reg 8 $ num[7:0] $end
$var reg 7 % disp0[6:0] $end
$var reg 7 & disp1[6:0] $end
$scope module t0 $end
$var reg 4 ' a[3:0] $end
$var reg 7 ( hex[6:0] $end
$upscope $end
$scope module t1 $end
$var reg 4 ) a[3:0] $end
$var reg 7 * hex[6:0] $end
$upscope $end
$scope module t2 $end
$var reg 1 + clk $end
$var reg 1 , reset $end
$var reg 1 - enable $end
$var reg 8 . q[7:0] $end
$var reg 8 / cnt[7:0] $end
$upscope $end
$upscope $end
$enddefinitions $end
#0
0!
1"
1#
b00000000 $
b1000000 %
b1000000 &
b0000 '
b1000000 (
b0000 )
b1000000 *
0+
1,
1-
b00000000 .
b00000000 /
#5000000
1!
0"
b00000001 $
b1111001 %
b0001 '
b1111001 (
1+
0,
b00000001 .
b00000001 /
#10000000
0!
0+
#15000000
1!
b00000010 $
b0100100 %
b0010 '
b0100100 (
1+
b00000010 .
b00000010 /
#20000000
0!
0+
#25000000
1!
b00000011 $
b0110000 %
b0011 '
b0110000 (
1+
b00000011 .
b00000011 /
#30000000
0!
0+
#35000000
1!
b00000100 $
b0011001 %
b0100 '
b0011001 (
1+
b00000100 .
b00000100 /
#40000000
0!
0+
#45000000
1!
b00000101 $
b0010010 %
b0101 '
b0010010 (
1+
b00000101 .
b00000101 /
#50000000
0!
0+
#55000000
1!
b00000110 $
b0000010 %
b0110 '
b0000010 (
1+
b00000110 .
b00000110 /
#60000000
0!
0+
#65000000
1!
b00000111 $
b1111000 %
b0111 '
b1111000 (
1+
b00000111 .
b00000111 /
#70000000
0!
0+
#75000000
1!
b00001000 $
b0000000 %
b1000 '
b0000000 (
1+
b00001000 .
b00001000 /
#80000000
0!
0+
#85000000
1!
b00001001 $
b0011000 %
b1001 '
b0011000 (
1+
b00001001 .
b00001001 /
#90000000
0!
0+
#95000000
1!
b00001010 $
b0001000 %
b1010 '
b0001000 (
1+
b00001010 .
b00001010 /
#100000000
0!
0+
#105000000
1!
b00001011 $
b0000011 %
b1011 '
b0000011 (
1+
b00001011 .
b00001011 /
#110000000
0!
0+
#115000000
1!
b00001100 $
b1000110 %
b1100 '
b1000110 (
1+
b00001100 .
b00001100 /
#120000000
0!
0+
#125000000
1!
b00001101 $
b0100001 %
b1101 '
b0100001 (
1+
b00001101 .
b00001101 /
#130000000
0!
0+
#135000000
1!
b00001110 $
b0000110 %
b1110 '
b0000110 (
1+
b00001110 .
b00001110 /
#140000000
0!
0+
#145000000
1!
b00001111 $
b0001110 %
b1111 '
b0001110 (
1+
b00001111 .
b00001111 /
#150000000
0!
0+
#155000000
1!
b00010000 $
b1000000 %
b1111001 &
b0000 '
b1000000 (
b0001 )
b1111001 *
1+
b00010000 .
b00010000 /
#160000000
0!
0+
#165000000
1!
b00010001 $
b1111001 %
b0001 '
b1111001 (
1+
b00010001 .
b00010001 /
#170000000
0!
0+
#175000000
1!
b00010010 $
b0100100 %
b0010 '
b0100100 (
1+
b00010010 .
b00010010 /
#180000000
0!
0+
#185000000
1!
b00010011 $
b0110000 %
b0011 '
b0110000 (
1+
b00010011 .
b00010011 /
#190000000
0!
0+
#195000000
1!
b00010100 $
b0011001 %
b0100 '
b0011001 (
1+
b00010100 .
b00010100 /
#200000000
0!
0+
#205000000
1!
b00010101 $
b0010010 %
b0101 '
b0010010 (
1+
b00010101 .
b00010101 /
#210000000
0!
0+
#215000000
1!
b00010110 $
b0000010 %
b0110 '
b0000010 (
1+
b00010110 .
b00010110 /
#220000000
0!
0+
#225000000
1!
b00010111 $
b1111000 %
b0111 '
b1111000 (
1+
b00010111 .
b00010111 /
#230000000
0!
0+
#235000000
1!
b00011000 $
b0000000 %
b1000 '
b0000000 (
1+
b00011000 .
b00011000 /
#240000000
0!
0+
#245000000
1!
b00011001 $
b0011000 %
b1001 '
b0011000 (
1+
b00011001 .
b00011001 /
#250000000
0!
0+
#255000000
1!
b00011010 $
b0001000 %
b1010 '
b0001000 (
1+
b00011010 .
b00011010 /
#260000000
0!
0+
#265000000
1!
b00011011 $
b0000011 %
b1011 '
b0000011 (
1+
b00011011 .
b00011011 /
#270000000
0!
0+
#275000000
1!
b00011100 $
b1000110 %
b1100 '
b1000110 (
1+
b00011100 .
b00011100 /
#280000000
0!
0+
#285000000
1!
b00011101 $
b0100001 %
b1101 '
b0100001 (
1+
b00011101 .
b00011101 /
#290000000
0!
0+
#295000000
1!
b00011110 $
b0000110 %
b1110 '
b0000110 (
1+
b00011110 .
b00011110 /
#300000000
0!
0+
#305000000
1!
b00011111 $
b0001110 %
b1111 '
b0001110 (
1+
b00011111 .
b00011111 /
#310000000
0!
0+
#315000000
1!
b00100000 $
b1000000 %
b0100100 &
b0000 '
b1000000 (
b0010 )
b0100100 *
1+
b00100000 .
b00100000 /
#320000000
0!
0+
#325000000
1!
b00100001 $
b1111001 %
b0001 '
b1111001 (
1+
b00100001 .
b00100001 /
#330000000
0!
0+
#335000000
1!
b00100010 $
b0100100 %
b0010 '
b0100100 (
1+
b00100010 .
b00100010 /
#340000000
0!
0+
#345000000
1!
b00100011 $
b0110000 %
b0011 '
b0110000 (
1+
b00100011 .
b00100011 /
#350000000
0!
0+
#355000000
1!
b00100100 $
b0011001 %
b0100 '
b0011001 (
1+
b00100100 .
b00100100 /
#360000000
0!
0+
#365000000
1!
b00100101 $
b0010010 %
b0101 '
b0010010 (
1+
b00100101 .
b00100101 /
#370000000
0!
0+
#375000000
1!
b00100110 $
b0000010 %
b0110 '
b0000010 (
1+
b00100110 .
b00100110 /
#380000000
0!
0+
#385000000
1!
b00100111 $
b1111000 %
b0111 '
b1111000 (
1+
b00100111 .
b00100111 /
#390000000
0!
0+
#395000000
1!
b00101000 $
b0000000 %
b1000 '
b0000000 (
1+
b00101000 .
b00101000 /
#400000000
0!
0+
#405000000
1!
b00101001 $
b0011000 %
b1001 '
b0011000 (
1+
b00101001 .
b00101001 /
#410000000
0!
0+
#415000000
1!
b00101010 $
b0001000 %
b1010 '
b0001000 (
1+
b00101010 .
b00101010 /
#420000000
0!
0+
#425000000
1!
b00101011 $
b0000011 %
b1011 '
b0000011 (
1+
b00101011 .
b00101011 /
#430000000
0!
0+
#435000000
1!
b00101100 $
b1000110 %
b1100 '
b1000110 (
1+
b00101100 .
b00101100 /
#440000000
0!
0+
#445000000
1!
b00101101 $
b0100001 %
b1101 '
b0100001 (
1+
b00101101 .
b00101101 /
#450000000
0!
0+
#455000000
1!
b00101110 $
b0000110 %
b1110 '
b0000110 (
1+
b00101110 .
b00101110 /
#460000000
0!
0+
#465000000
1!
b00101111 $
b0001110 %
b1111 '
b0001110 (
1+
b00101111 .
b00101111 /
#470000000
0!
0+
#475000000
1!
b00110000 $
b1000000 %
b0110000 &
b0000 '
b1000000 (
b0011 )
b0110000 *
1+
b00110000 .
b00110000 /
#480000000
0!
0+
#485000000
1!
b00110001 $
b1111001 %
b0001 '
b1111001 (
1+
b00110001 .
b00110001 /
#490000000
0!
0+
#495000000
1!
b00110010 $
b0100100 %
b0010 '
b0100100 (
1+
b00110010 .
b00110010 /
#500000000
0!
0+
#505000000
1!
b00110011 $
b0110000 %
b0011 '
b0110000 (
1+
b00110011 .
b00110011 /
#510000000
0!
0+
#515000000
1!
b00110100 $
b0011001 %
b0100 '
b0011001 (
1+
b00110100 .
b00110100 /
#520000000
0!
0+
#525000000
1!
b00110101 $
b0010010 %
b0101 '
b0010010 (
1+
b00110101 .
b00110101 /
#530000000
0!
0+
#535000000
1!
b00110110 $
b0000010 %
b0110 '
b0000010 (
1+
b00110110 .
b00110110 /
#540000000
0!
0+
#545000000
1!
b00110111 $
b1111000 %
b0111 '
b1111000 (
1+
b00110111 .
b00110111 /
#550000000
0!
0+
#555000000
1!
b00111000 $
b0000000 %
b1000 '
b0000000 (
1+
b00111000 .
b00111000 /
#560000000
0!
0+
#565000000
1!
b00111001 $
b0011000 %
b1001 '
b0011000 (
1+
b00111001 .
b00111001 /
#570000000
0!
0+
#575000000
1!
b00111010 $
b0001000 %
b1010 '
b0001000 (
1+
b00111010 .
b00111010 /
#580000000
0!
0+
#585000000
1!
b00111011 $
b0000011 %
b1011 '
b0000011 (
1+
b00111011 .
b00111011 /
#590000000
0!
0+
#595000000
1!
b00111100 $
b1000110 %
b1100 '
b1000110 (
1+
b00111100 .
b00111100 /
#600000000
0!
0+
#605000000
1!
b00111101 $
b0100001 %
b1101 '
b0100001 (
1+
b00111101 .
b00111101 /
#610000000
0!
0+
#615000000
1!
b00111110 $
b0000110 %
b1110 '
b0000110 (
1+
b00111110 .
b00111110 /
#620000000
0!
0+
#625000000
1!
b00111111 $
b0001110 %
b1111 '
b0001110 (
1+
b00111111 .
b00111111 /
#630000000
0!
0+
#635000000
1!
b01000000 $
b1000000 %
b0011001 &
b0000 '
b1000000 (
b0100 )
b0011001 *
1+
b01000000 .
b01000000 /
#640000000
0!
0+
#645000000
1!
b01000001 $
b1111001 %
b0001 '
b1111001 (
1+
b01000001 .
b01000001 /
#650000000
0!
0+
#655000000
1!
b01000010 $
b0100100 %
b0010 '
b0100100 (
1+
b01000010 .
b01000010 /
#660000000
0!
0+
#665000000
1!
b01000011 $
b0110000 %
b0011 '
b0110000 (
1+
b01000011 .
b01000011 /
#670000000
0!
0+
#675000000
1!
b01000100 $
b0011001 %
b0100 '
b0011001 (
1+
b01000100 .
b01000100 /
#680000000
0!
0+
#685000000
1!
b01000101 $
b0010010 %
b0101 '
b0010010 (
1+
b01000101 .
b01000101 /
#690000000
0!
0+
#695000000
1!
b01000110 $
b0000010 %
b0110 '
b0000010 (
1+
b01000110 .
b01000110 /
#700000000
0!
0+
#705000000
1!
b01000111 $
b1111000 %
b0111 '
b1111000 (
1+
b01000111 .
b01000111 /
#710000000
0!
0+
#715000000
1!
b01001000 $
b0000000 %
b1000 '
b0000000 (
1+
b01001000 .
b01001000 /
#720000000
0!
0+
#725000000
1!
b01001001 $
b0011000 %
b1001 '
b0011000 (
1+
b01001001 .
b01001001 /
#730000000
0!
0+
#735000000
1!
b01001010 $
b0001000 %
b1010 '
b0001000 (
1+
b01001010 .
b01001010 /
#740000000
0!
0+
#745000000
1!
b01001011 $
b0000011 %
b1011 '
b0000011 (
1+
b01001011 .
b01001011 /
#750000000
0!
0+
#755000000
1!
b01001100 $
b1000110 %
b1100 '
b1000110 (
1+
b01001100 .
b01001100 /
#760000000
0!
0+
#765000000
1!
b01001101 $
b0100001 %
b1101 '
b0100001 (
1+
b01001101 .
b01001101 /
#770000000
0!
0+
#775000000
1!
b01001110 $
b0000110 %
b1110 '
b0000110 (
1+
b01001110 .
b01001110 /
#780000000
0!
0+
#785000000
1!
b01001111 $
b0001110 %
b1111 '
b0001110 (
1+
b01001111 .
b01001111 /
#790000000
0!
0+
#795000000
1!
b01010000 $
b1000000 %
b0010010 &
b0000 '
b1000000 (
b0101 )
b0010010 *
1+
b01010000 .
b01010000 /
#800000000
0!
0+
#805000000
1!
b01010001 $
b1111001 %
b0001 '
b1111001 (
1+
b01010001 .
b01010001 /
#810000000
0!
0+
#815000000
1!
b01010010 $
b0100100 %
b0010 '
b0100100 (
1+
b01010010 .
b01010010 /
#820000000
0!
0+
#825000000
1!
b01010011 $
b0110000 %
b0011 '
b0110000 (
1+
b01010011 .
b01010011 /
#830000000
0!
0+
#835000000
1!
b01010100 $
b0011001 %
b0100 '
b0011001 (
1+
b01010100 .
b01010100 /
#840000000
0!
0+
#845000000
1!
b01010101 $
b0010010 %
b0101 '
b0010010 (
1+
b01010101 .
b01010101 /
#850000000
0!
0+
#855000000
1!
b01010110 $
b0000010 %
b0110 '
b0000010 (
1+
b01010110 .
b01010110 /
#860000000
0!
0+
#865000000
1!
b01010111 $
b1111000 %
b0111 '
b1111000 (
1+
b01010111 .
b01010111 /
#870000000
0!
0+
#875000000
1!
b01011000 $
b0000000 %
b1000 '
b0000000 (
1+
b01011000 .
b01011000 /
#880000000
0!
0+
#885000000
1!
b01011001 $
b0011000 %
b1001 '
b0011000 (
1+
b01011001 .
b01011001 /
#890000000
0!
0+
#895000000
1!
b01011010 $
b0001000 %
b1010 '
b0001000 (
1+
b01011010 .
b01011010 /
#900000000
0!
0+
#905000000
1!
b01011011 $
b0000011 %
b1011 '
b0000011 (
1+
b01011011 .
b01011011 /
#910000000
0!
0+
#915000000
1!
b01011100 $
b1000110 %
b1100 '
b1000110 (
1+
b01011100 .
b01011100 /
#920000000
0!
0+
#925000000
1!
b01011101 $
b0100001 %
b1101 '
b0100001 (
1+
b01011101 .
b01011101 /
#930000000
0!
0+
#935000000
1!
b01011110 $
b0000110 %
b1110 '
b0000110 (
1+
b01011110 .
b01011110 /
#940000000
0!
0+
#945000000
1!
b01011111 $
b0001110 %
b1111 '
b0001110 (
1+
b01011111 .
b01011111 /
#950000000
0!
0+
#955000000
1!
b01100000 $
b1000000 %
b0000010 &
b0000 '
b1000000 (
b0110 )
b0000010 *
1+
b01100000 .
b01100000 /
#960000000
0!
0+
#965000000
1!
b01100001 $
b1111001 %
b0001 '
b1111001 (
1+
b01100001 .
b01100001 /
#970000000
0!
0+
#975000000
1!
b01100010 $
b0100100 %
b0010 '
b0100100 (
1+
b01100010 .
b01100010 /
#980000000
0!
0+
#985000000
1!
b01100011 $
b0110000 %
b0011 '
b0110000 (
1+
b01100011 .
b01100011 /
#990000000
0!
0+
#995000000
1!
b01100100 $
b0011001 %
b0100 '
b0011001 (
1+
b01100100 .
b01100100 /
#1000000000
0!
0+
#1005000000
1!
b01100101 $
b0010010 %
b0101 '
b0010010 (
1+
b01100101 .
b01100101 /
#1010000000
0!
0+
#1015000000
1!
b01100110 $
b0000010 %
b0110 '
b0000010 (
1+
b01100110 .
b01100110 /
#1020000000
0!
0+
#1025000000
1!
b01100111 $
b1111000 %
b0111 '
b1111000 (
1+
b01100111 .
b01100111 /
#1030000000
0!
0+
#1035000000
1!
b01101000 $
b0000000 %
b1000 '
b0000000 (
1+
b01101000 .
b01101000 /
#1040000000
0!
0+
#1045000000
1!
b01101001 $
b0011000 %
b1001 '
b0011000 (
1+
b01101001 .
b01101001 /
#1050000000
0!
0+
#1055000000
1!
b01101010 $
b0001000 %
b1010 '
b0001000 (
1+
b01101010 .
b01101010 /
#1060000000
0!
0+
#1065000000
1!
b01101011 $
b0000011 %
b1011 '
b0000011 (
1+
b01101011 .
b01101011 /
#1070000000
0!
0+
#1075000000
1!
b01101100 $
b1000110 %
b1100 '
b1000110 (
1+
b01101100 .
b01101100 /
#1080000000
0!
0+
#1085000000
1!
b01101101 $
b0100001 %
b1101 '
b0100001 (
1+
b01101101 .
b01101101 /
#1090000000
0!
0+
#1095000000
1!
b01101110 $
b0000110 %
b1110 '
b0000110 (
1+
b01101110 .
b01101110 /
#1100000000
0!
0+
#1105000000
1!
b01101111 $
b0001110 %
b1111 '
b0001110 (
1+
b01101111 .
b01101111 /
#1110000000
0!
0+
#1115000000
1!
b01110000 $
b1000000 %
b1111000 &
b0000 '
b1000000 (
b0111 )
b1111000 *
1+
b01110000 .
b01110000 /
#1120000000
0!
0+
#1125000000
1!
b01110001 $
b1111001 %
b0001 '
b1111001 (
1+
b01110001 .
b01110001 /
#1130000000
0!
0+
#1135000000
1!
b01110010 $
b0100100 %
b0010 '
b0100100 (
1+
b01110010 .
b01110010 /
#1140000000
0!
0+
#1145000000
1!
b01110011 $
b0110000 %
b0011 '
b0110000 (
1+
b01110011 .
b01110011 /
#1150000000
0!
0+
#1155000000
1!
b01110100 $
b0011001 %
b0100 '
b0011001 (
1+
b01110100 .
b01110100 /
#1160000000
0!
0+
#1165000000
1!
b01110101 $
b0010010 %
b0101 '
b0010010 (
1+
b01110101 .
b01110101 /
#1170000000
0!
0+
#1175000000
1!
b01110110 $
b0000010 %
b0110 '
b0000010 (
1+
b01110110 .
b01110110 /
#1180000000
0!
0+
#1185000000
1!
b01110111 $
b1111000 %
b0111 '
b1111000 (
1+
b01110111 .
b01110111 /
#1190000000
0!
0+
#1195000000
1!
b01111000 $
b0000000 %
b1000 '
b0000000 (
1+
b01111000 .
b01111000 /
#1200000000
0!
0+
#1205000000
1!
b01111001 $
b0011000 %
b1001 '
b0011000 (
1+
b01111001 .
b01111001 /
#1210000000
0!
0+
#1215000000
1!
b01111010 $
b0001000 %
b1010 '
b0001000 (
1+
b01111010 .
b01111010 /
#1220000000
0!
0+
#1225000000
1!
b01111011 $
b0000011 %
b1011 '
b0000011 (
1+
b01111011 .
b01111011 /
#1230000000
0!
0+
#1235000000
1!
b01111100 $
b1000110 %
b1100 '
b1000110 (
1+
b01111100 .
b01111100 /
#1240000000
0!
0+
#1245000000
1!
b01111101 $
b0100001 %
b1101 '
b0100001 (
1+
b01111101 .
b01111101 /
#1250000000
0!
0+
#1255000000
1!
b01111110 $
b0000110 %
b1110 '
b0000110 (
1+
b01111110 .
b01111110 /
#1260000000
0!
0+
#1265000000
1!
b01111111 $
b0001110 %
b1111 '
b0001110 (
1+
b01111111 .
b01111111 /
#1270000000
0!
0+
#1275000000
1!
b10000000 $
b1000000 %
b0000000 &
b0000 '
b1000000 (
b1000 )
b0000000 *
1+
b10000000 .
b10000000 /
#1280000000
0!
0+
#1285000000
1!
b10000001 $
b1111001 %
b0001 '
b1111001 (
1+
b10000001 .
b10000001 /
#1290000000
0!
0+
#1295000000
1!
b10000010 $
b0100100 %
b0010 '
b0100100 (
1+
b10000010 .
b10000010 /
#1300000000
0!
0+
#1305000000
1!
b10000011 $
b0110000 %
b0011 '
b0110000 (
1+
b10000011 .
b10000011 /
#1310000000
0!
0+
#1315000000
1!
b10000100 $
b0011001 %
b0100 '
b0011001 (
1+
b10000100 .
b10000100 /
#1320000000
0!
0+
#1325000000
1!
b10000101 $
b0010010 %
b0101 '
b0010010 (
1+
b10000101 .
b10000101 /
#1330000000
0!
0+
#1335000000
1!
b10000110 $
b0000010 %
b0110 '
b0000010 (
1+
b10000110 .
b10000110 /
#1340000000
0!
0+
#1345000000
1!
b10000111 $
b1111000 %
b0111 '
b1111000 (
1+
b10000111 .
b10000111 /
#1350000000
0!
0+
#1355000000
1!
b10001000 $
b0000000 %
b1000 '
b0000000 (
1+
b10001000 .
b10001000 /
#1360000000
0!
0+
#1365000000
1!
b10001001 $
b0011000 %
b1001 '
b0011000 (
1+
b10001001 .
b10001001 /
#1370000000
0!
0+
#1375000000
1!
b10001010 $
b0001000 %
b1010 '
b0001000 (
1+
b10001010 .
b10001010 /
#1380000000
0!
0+
#1385000000
1!
b10001011 $
b0000011 %
b1011 '
b0000011 (
1+
b10001011 .
b10001011 /
#1390000000
0!
0+
#1395000000
1!
b10001100 $
b1000110 %
b1100 '
b1000110 (
1+
b10001100 .
b10001100 /
#1400000000
0!
0+
#1405000000
1!
b10001101 $
b0100001 %
b1101 '
b0100001 (
1+
b10001101 .
b10001101 /
#1410000000
0!
0+
#1415000000
1!
b10001110 $
b0000110 %
b1110 '
b0000110 (
1+
b10001110 .
b10001110 /
#1420000000
0!
0+
#1425000000
1!
b10001111 $
b0001110 %
b1111 '
b0001110 (
1+
b10001111 .
b10001111 /
#1430000000
0!
0+
#1435000000
1!
b10010000 $
b1000000 %
b0011000 &
b0000 '
b1000000 (
b1001 )
b0011000 *
1+
b10010000 .
b10010000 /
#1440000000
0!
0+
#1445000000
1!
b10010001 $
b1111001 %
b0001 '
b1111001 (
1+
b10010001 .
b10010001 /
#1450000000
0!
0+
#1455000000
1!
b10010010 $
b0100100 %
b0010 '
b0100100 (
1+
b10010010 .
b10010010 /
#1460000000
0!
0+
#1465000000
1!
b10010011 $
b0110000 %
b0011 '
b0110000 (
1+
b10010011 .
b10010011 /
#1470000000
0!
0+
#1475000000
1!
b10010100 $
b0011001 %
b0100 '
b0011001 (
1+
b10010100 .
b10010100 /
#1480000000
0!
0+
#1485000000
1!
b10010101 $
b0010010 %
b0101 '
b0010010 (
1+
b10010101 .
b10010101 /
#1490000000
0!
0+
#1495000000
1!
b10010110 $
b0000010 %
b0110 '
b0000010 (
1+
b10010110 .
b10010110 /
#1500000000
0!
0+
#1505000000
1!
b10010111 $
b1111000 %
b0111 '
b1111000 (
1+
b10010111 .
b10010111 /
#1510000000
0!
0+
#1515000000
1!
b10011000 $
b0000000 %
b1000 '
b0000000 (
1+
b10011000 .
b10011000 /
#1520000000
0!
0+
#1525000000
1!
b10011001 $
b0011000 %
b1001 '
b0011000 (
1+
b10011001 .
b10011001 /
#1530000000
0!
0+
#1535000000
1!
b10011010 $
b0001000 %
b1010 '
b0001000 (
1+
b10011010 .
b10011010 /
#1540000000
0!
0+
#1545000000
1!
b10011011 $
b0000011 %
b1011 '
b0000011 (
1+
b10011011 .
b10011011 /
#1550000000
0!
0+
#1555000000
1!
b10011100 $
b1000110 %
b1100 '
b1000110 (
1+
b10011100 .
b10011100 /
#1560000000
0!
0+
#1565000000
1!
b10011101 $
b0100001 %
b1101 '
b0100001 (
1+
b10011101 .
b10011101 /
#1570000000
0!
0+
#1575000000
1!
b10011110 $
b0000110 %
b1110 '
b0000110 (
1+
b10011110 .
b10011110 /
#1580000000
0!
0+
#1585000000
1!
b10011111 $
b0001110 %
b1111 '
b0001110 (
1+
b10011111 .
b10011111 /
#1590000000
0!
0+
#1595000000
1!
b10100000 $
b1000000 %
b0001000 &
b0000 '
b1000000 (
b1010 )
b0001000 *
1+
b10100000 .
b10100000 /
#1600000000
0!
0+
#1605000000
1!
b10100001 $
b1111001 %
b0001 '
b1111001 (
1+
b10100001 .
b10100001 /
#1610000000
0!
0+
#1615000000
1!
b10100010 $
b0100100 %
b0010 '
b0100100 (
1+
b10100010 .
b10100010 /
#1620000000
0!
0+
#1625000000
1!
b10100011 $
b0110000 %
b0011 '
b0110000 (
1+
b10100011 .
b10100011 /
#1630000000
0!
0+
#1635000000
1!
b10100100 $
b0011001 %
b0100 '
b0011001 (
1+
b10100100 .
b10100100 /
#1640000000
0!
0+
#1645000000
1!
b10100101 $
b0010010 %
b0101 '
b0010010 (
1+
b10100101 .
b10100101 /
#1650000000
0!
0+
#1655000000
1!
b10100110 $
b0000010 %
b0110 '
b0000010 (
1+
b10100110 .
b10100110 /
#1660000000
0!
0+
#1665000000
1!
b10100111 $
b1111000 %
b0111 '
b1111000 (
1+
b10100111 .
b10100111 /
#1670000000
0!
0+
#1675000000
1!
b10101000 $
b0000000 %
b1000 '
b0000000 (
1+
b10101000 .
b10101000 /
#1680000000
0!
0+
#1685000000
1!
b10101001 $
b0011000 %
b1001 '
b0011000 (
1+
b10101001 .
b10101001 /
#1690000000
0!
0+
#1695000000
1!
b10101010 $
b0001000 %
b1010 '
b0001000 (
1+
b10101010 .
b10101010 /
#1700000000
0!
0+
#1705000000
1!
b10101011 $
b0000011 %
b1011 '
b0000011 (
1+
b10101011 .
b10101011 /
#1710000000
0!
0+
#1715000000
1!
b10101100 $
b1000110 %
b1100 '
b1000110 (
1+
b10101100 .
b10101100 /
#1720000000
0!
0+
#1725000000
1!
b10101101 $
b0100001 %
b1101 '
b0100001 (
1+
b10101101 .
b10101101 /
#1730000000
0!
0+
#1735000000
1!
b10101110 $
b0000110 %
b1110 '
b0000110 (
1+
b10101110 .
b10101110 /
#1740000000
0!
0+
#1745000000
1!
b10101111 $
b0001110 %
b1111 '
b0001110 (
1+
b10101111 .
b10101111 /
#1750000000
0!
0+
#1755000000
1!
b10110000 $
b1000000 %
b0000011 &
b0000 '
b1000000 (
b1011 )
b0000011 *
1+
b10110000 .
b10110000 /
#1760000000
0!
0+
#1765000000
1!
b10110001 $
b1111001 %
b0001 '
b1111001 (
1+
b10110001 .
b10110001 /
#1770000000
0!
0+
#1775000000
1!
b10110010 $
b0100100 %
b0010 '
b0100100 (
1+
b10110010 .
b10110010 /
#1780000000
0!
0+
#1785000000
1!
b10110011 $
b0110000 %
b0011 '
b0110000 (
1+
b10110011 .
b10110011 /
#1790000000
0!
0+
#1795000000
1!
b10110100 $
b0011001 %
b0100 '
b0011001 (
1+
b10110100 .
b10110100 /
#1800000000
0!
0+
#1805000000
1!
b10110101 $
b0010010 %
b0101 '
b0010010 (
1+
b10110101 .
b10110101 /
#1810000000
0!
0+
#1815000000
1!
b10110110 $
b0000010 %
b0110 '
b0000010 (
1+
b10110110 .
b10110110 /
#1820000000
0!
0+
#1825000000
1!
b10110111 $
b1111000 %
b0111 '
b1111000 (
1+
b10110111 .
b10110111 /
#1830000000
0!
0+
#1835000000
1!
b10111000 $
b0000000 %
b1000 '
b0000000 (
1+
b10111000 .
b10111000 /
#1840000000
0!
0+
#1845000000
1!
b10111001 $
b0011000 %
b1001 '
b0011000 (
1+
b10111001 .
b10111001 /
#1850000000
0!
0+
#1855000000
1!
b10111010 $
b0001000 %
b1010 '
b0001000 (
1+
b10111010 .
b10111010 /
#1860000000
0!
0+
#1865000000
1!
b10111011 $
b0000011 %
b1011 '
b0000011 (
1+
b10111011 .
b10111011 /
#1870000000
0!
0+
#1875000000
1!
b10111100 $
b1000110 %
b1100 '
b1000110 (
1+
b10111100 .
b10111100 /
#1880000000
0!
0+
#1885000000
1!
b10111101 $
b0100001 %
b1101 '
b0100001 (
1+
b10111101 .
b10111101 /
#1890000000
0!
0+
#1895000000
1!
b10111110 $
b0000110 %
b1110 '
b0000110 (
1+
b10111110 .
b10111110 /
#1900000000
0!
0+
#1905000000
1!
b10111111 $
b0001110 %
b1111 '
b0001110 (
1+
b10111111 .
b10111111 /
#1910000000
0!
0+
#1915000000
1!
b11000000 $
b1000000 %
b1000110 &
b0000 '
b1000000 (
b1100 )
b1000110 *
1+
b11000000 .
b11000000 /
#1920000000
0!
0+
#1925000000
1!
b11000001 $
b1111001 %
b0001 '
b1111001 (
1+
b11000001 .
b11000001 /
#1930000000
0!
0+
#1935000000
1!
b11000010 $
b0100100 %
b0010 '
b0100100 (
1+
b11000010 .
b11000010 /
#1940000000
0!
0+
#1945000000
1!
b11000011 $
b0110000 %
b0011 '
b0110000 (
1+
b11000011 .
b11000011 /
#1950000000
0!
0+
#1955000000
1!
b11000100 $
b0011001 %
b0100 '
b0011001 (
1+
b11000100 .
b11000100 /
#1960000000
0!
0+
#1965000000
1!
b11000101 $
b0010010 %
b0101 '
b0010010 (
1+
b11000101 .
b11000101 /
#1970000000
0!
0+
#1975000000
1!
b11000110 $
b0000010 %
b0110 '
b0000010 (
1+
b11000110 .
b11000110 /
#1980000000
0!
0+
#1985000000
1!
b11000111 $
b1111000 %
b0111 '
b1111000 (
1+
b11000111 .
b11000111 /
#1990000000
0!
0+
#1995000000
1!
b11001000 $
b0000000 %
b1000 '
b0000000 (
1+
b11001000 .
b11001000 /
#2000000000
0!
0+
