Project02/counter7.vhd
library ieee;
use ieee.std_logic_1164.all;
use ieee.numeric_std.all;

entity counter7 is

  port
    (
      clk         : in std_logic;
      reset	  : in std_logic;
      enable	  : in std_logic;
      q  	      : out unsigned(6 downto 0)
      );

end entity;

architecture rtl of counter7 is
    signal cnt : unsigned(6 downto 0);
begin

  process (clk)
  begin
    if reset = '1' then
      -- Reset the counter to 0
      cnt <= "0000000";
    elsif (rising_edge(clk)) then
      if enable = '1' then
        -- Increment the counter if counting is enabled			   
        cnt <= cnt + 1;
      end if;
    end if;
  end process;
  
  q <= cnt;

end rtl;

Project03/hexdisplay.vhd
library IEEE;
use IEEE.std_logic_1164.all;
use IEEE.numeric_std.all;

entity hexdisplay is
	port (
			A	 :	in  unsigned(3 downto 0);
			hex : out unsigned(6 downto 0)
			);
end hexdisplay;

architecture test of hexdisplay is			
begin
		hex	<= 
			"1000000" when A = "0000" else
			"1111001" when A = "0001" else
			"0100100" when A = "0010" else
			"0110000" when A = "0011" else
			"0011001" when A = "0100" else
			"0010010" when A = "0101" else
			"0000010" when A = "0110" else
			"1111000" when A = "0111" else
			"0000000" when A = "1000" else
			"0011000" when A = "1001" else
			"0001000" when A = "1010" else
			"0000011" when A = "1011" else
			"1000110" when A = "1100" else
			"0100001" when A = "1101" else
			"0000110" when A = "1110" else
			"0001110" when A = "1111";		

end test;

Project02/hexbench.vhd
library ieee;
use ieee.std_logic_1164.all;
use ieee.numeric_std.all;

entity hexbench is
end hexbench;

architecture one of hexbench is

  constant num_cycles : integer := 15;  -- run for 40 clock cycles

  -- this circuit needs a clock, enable, and a reset
  -- for the counter
  signal clk      : std_logic := '1';
  signal reset, enable: std_logic;
  -- signal for count
  signal num : unsigned(6 downto 0);
  -- signals for each hex display
  signal disp0 : unsigned(6 downto 0);

  component hexdisplay
  port(
    A :  IN UNSIGNED(3 downto 0);
    hex: OUT UNSIGNED(6 downto 0)
    );
  end component;
  
  component counter7 is
  port
    (
      clk         : in std_logic;
      reset	  : in std_logic;
      enable	  : in std_logic;
      q  	      : out unsigned(6 downto 0)
      );
end component;

begin

  -- start off with a short reset
  reset <= '1', '0' after 5 ns;

  enable <= '1';

  -- create a clock
  process begin
    for i in 1 to num_cycles loop
      clk <= not clk;
      wait for 5 ns;
      clk <= not clk;
      wait for 5 ns;
    end loop;
    wait;
  end process;

T0: hexdisplay port map(num(3 downto 0),disp0);
T1: counter7 port map(clk,reset,enable,num);

end one;

Project02/hexbench.vcd
$date
  Sun Oct  2 13:36:39 2022
$end
$version
  GHDL v0
$end
$timescale
  1 fs
$end
$scope module standard $end
$upscope $end
$scope module std_logic_1164 $end
$upscope $end
$scope module numeric_std $end
$upscope $end
$scope module hexbench $end
$var reg 1 ! clk $end
$var reg 1 " reset $end
$var reg 1 # enable $end
$var reg 7 $ num[6:0] $end
$var reg 7 % disp0[6:0] $end
$scope module t0 $end
$var reg 4 & a[3:0] $end
$var reg 7 ' hex[6:0] $end
$upscope $end
$scope module t1 $end
$var reg 1 ( clk $end
$var reg 1 ) reset $end
$var reg 1 * enable $end
$var reg 7 + q[6:0] $end
$var reg 7 , cnt[6:0] $end
$upscope $end
$upscope $end
$enddefinitions $end
#0
0!
1"
1#
b0000000 $
b1000000 %
b0000 &
b1000000 '
0(
1)
1*
b0000000 +
b0000000 ,
#5000000
1!
0"
b0000001 $
b1111001 %
b0001 &
b1111001 '
1(
0)
b0000001 +
b0000001 ,
#10000000
0!
0(
#15000000
1!
b0000010 $
b0100100 %
b0010 &
b0100100 '
1(
b0000010 +
b0000010 ,
#20000000
0!
0(
#25000000
1!
b0000011 $
b0110000 %
b0011 &
b0110000 '
1(
b0000011 +
b0000011 ,
#30000000
0!
0(
#35000000
1!
b0000100 $
b0011001 %
b0100 &
b0011001 '
1(
b0000100 +
b0000100 ,
#40000000
0!
0(
#45000000
1!
b0000101 $
b0010010 %
b0101 &
b0010010 '
1(
b0000101 +
b0000101 ,
#50000000
0!
0(
#55000000
1!
b0000110 $
b0000010 %
b0110 &
b0000010 '
1(
b0000110 +
b0000110 ,
#60000000
0!
0(
#65000000
1!
b0000111 $
b1111000 %
b0111 &
b1111000 '
1(
b0000111 +
b0000111 ,
#70000000
0!
0(
#75000000
1!
b0001000 $
b0000000 %
b1000 &
b0000000 '
1(
b0001000 +
b0001000 ,
#80000000
0!
0(
#85000000
1!
b0001001 $
b0011000 %
b1001 &
b0011000 '
1(
b0001001 +
b0001001 ,
#90000000
0!
0(
#95000000
1!
b0001010 $
b0001000 %
b1010 &
b0001000 '
1(
b0001010 +
b0001010 ,
#100000000
0!
0(
#105000000
1!
b0001011 $
b0000011 %
b1011 &
b0000011 '
1(
b0001011 +
b0001011 ,
#110000000
0!
0(
#115000000
1!
b0001100 $
b1000110 %
b1100 &
b1000110 '
1(
b0001100 +
b0001100 ,
#120000000
0!
0(
#125000000
1!
b0001101 $
b0100001 %
b1101 &
b0100001 '
1(
b0001101 +
b0001101 ,
#130000000
0!
0(
#135000000
1!
b0001110 $
b0000110 %
b1110 &
b0000110 '
1(
b0001110 +
b0001110 ,
#140000000
0!
0(
#145000000
1!
b0001111 $
b0001110 %
b1111 &
b0001110 '
1(
b0001111 +
b0001111 ,
