Project03/timer.vhd
-- Quartus II VHDL Template
-- Four-State Moore State Machine

-- A Moore machine's outputs are dependent only on the current state.
-- The output is written only when the state changes.  (State
-- transitions are synchronous.)

library ieee;
use ieee.std_logic_1164.all;
use ieee.numeric_std.all;

entity timer is

	port(
		clk	 : in	std_logic;
		reset	 : in	std_logic;
		start	 : in	std_logic;
		react  : in std_logic;
		sNum	 : out std_logic_vector(1	downto 0);
		cycles : out std_logic_vector(7 downto 0);
		red	 : out std_logic;
		green  : out std_logic
	);

end entity;

architecture rtl of timer is

	-- Build an enumerated type for the state machine
	type state_type is (sIdle, sWait, sCount);

	-- Register to hold the current state
	signal state   : state_type;
	
	signal count : unsigned (7 downto 0);
	

begin

	-- Logic to advance to the next state
	process (clk, reset, start, react)
	begin
		if reset = '0' then
				state <= sIdle;
				count <= (others=>'0');
		elsif (rising_edge(clk)) then
			count <= count + 1;
			case state is
				when sIdle=>
					if start = '0' then
						state <= sWait;
					else
						state <= sIdle;
					end if;
				when sWait=>
					if react = '0' then
						count <= (others=>'1');
						state <= sIdle;
					elsif count = "00001111" then
						state <= sCount;
						count <= (others=>'0');
					else
						state <= sWait;
					end if;
				when sCount=>
					if react = '0' then
						state <= sIdle;
					else
						state <= sCount;
					end if;
			end case;
		end if;
	end process;
	
-- Output depends solely on the current state
	process (state)
	begin
		case state is
			when sCount =>
				sNum <= "10";
				green  <= '1';
				red    <= '0';
				cycles <= std_logic_vector(count);
			when sWait =>
				sNum <= "01";
				green  <= '0';
				red    <= '1';
				cycles <= (others=>'0');
			when sIdle =>
				sNum <= "00";
				green <= '0';
				red   <= '0';
				cycles <= std_logic_vector(count);
		end case;
	end process;

end rtl;

Project03/hexdisplay.vhd
library IEEE;
use IEEE.std_logic_1164.all;
use IEEE.numeric_std.all;

entity hexdisplay is
	port (
			A	 :	in  unsigned(3 downto 0);
			hex : out unsigned(6 downto 0)
			);
end hexdisplay;

architecture test of hexdisplay is			
begin
		hex	<= 
			"1000000" when A = "0000" else
			"1111001" when A = "0001" else
			"0100100" when A = "0010" else
			"0110000" when A = "0011" else
			"0011001" when A = "0100" else
			"0010010" when A = "0101" else
			"0000010" when A = "0110" else
			"1111000" when A = "0111" else
			"0000000" when A = "1000" else
			"0011000" when A = "1001" else
			"0001000" when A = "1010" else
			"0000011" when A = "1011" else
			"1000110" when A = "1100" else
			"0100001" when A = "1101" else
			"0000110" when A = "1110" else
			"0001110" when A = "1111";		

end test;

Project03/timingtest.vhd
-- Bruce A. Maxwell
-- Spring 2013
-- CS 232 Lab 3
-- Test bench for the bright state machine circuit
--

library ieee;
use ieee.std_logic_1164.all;
use ieee.numeric_std.all;

-- a test bench has no inputs or outputs
entity timingtest is
end timingtest;

-- architecture
architecture test of timingtest is

  -- internal signals for everything we want to send to or receive from the
  -- test circuit
  signal reset, start, react: std_logic;
  signal cycles: std_logic_vector (7 downto 0);
  signal sNum: std_logic_vector (1 downto 0);
  signal red, green: std_logic;
  
  --display
  signal disp0: unsigned(6 downto 0);
  signal disp1: unsigned(6 downto 0);
  
  component hexdisplay
  port(
    A :  IN UNSIGNED(3 downto 0);
    hex: OUT UNSIGNED(6 downto 0)
    );
  end component;
  -- the component statement lets us instantiate a bright circuit
  component timer
    port(
      clk	 : in	std_logic;
		reset	 : in	std_logic;
		start	 : in	std_logic;
		react  : in std_logic;
		sNum	 : out std_logic_vector(1	downto 0);
		cycles : out std_logic_vector(7 downto 0);
		red	 : out std_logic;
		green  : out std_logic
      );
  end component;

  -- signals for making the clock
  constant num_cycles : integer := 50;
  signal clk : std_logic := '1';

begin

  -- these are timed signal assignments to create specific patterns
  reset <= '0', '1' after 20 ns, '0' after 250 ns, '1' after 270 ns;
  start <= '1', '0' after 20 ns, '1' after 50 ns, '0' after 280 ns, '1' after 300 ns;
  react <= '1', '0' after 200 ns, '1' after 220 ns, '0' after 350 ns, '1' after 370 ns;
  

  -- we can use a process and a for loop to generate a clock signal
  process begin
    for i in 1 to num_cycles loop
      clk <= not clk;
      wait for 5 ns;
      clk <= not clk;
      wait for 5 ns;
    end loop;
    wait;
  end process;

  -- this instantiates a bright circuit and sets up the inputs and outputs
  T0: hexdisplay port map(unsigned(cycles(3 downto 0)),disp0);
  T1: hexdisplay port map(unsigned(cycles(7 downto 4)),disp1);
  T2: timer port map (clk, reset, start, react, sNum, cycles, red, green);
end test;

Project03/timingtest.vcd
$date
  Mon Oct 17 22:33:35 2022
$end
$version
  GHDL v0
$end
$timescale
  1 fs
$end
$scope module standard $end
$upscope $end
$scope module std_logic_1164 $end
$upscope $end
$scope module numeric_std $end
$upscope $end
$scope module timingtest $end
$var reg 1 ! reset $end
$var reg 1 " start $end
$var reg 1 # react $end
$var reg 8 $ cycles[7:0] $end
$var reg 2 % snum[1:0] $end
$var reg 1 & red $end
$var reg 1 ' green $end
$var reg 7 ( disp0[6:0] $end
$var reg 7 ) disp1[6:0] $end
$var reg 1 * clk $end
$scope module t0 $end
$var reg 4 + a[3:0] $end
$var reg 7 , hex[6:0] $end
$upscope $end
$scope module t1 $end
$var reg 4 - a[3:0] $end
$var reg 7 . hex[6:0] $end
$upscope $end
$scope module t2 $end
$var reg 1 / clk $end
$var reg 1 0 reset $end
$var reg 1 1 start $end
$var reg 1 2 react $end
$var reg 2 3 snum[1:0] $end
$var reg 8 4 cycles[7:0] $end
$var reg 1 5 red $end
$var reg 1 6 green $end
$comment state is not handled $end
$var reg 8 7 count[7:0] $end
$upscope $end
$upscope $end
$enddefinitions $end
#0
0!
1"
1#
bUUUUUUUU $
b00 %
0&
0'
bUUUUUUU (
bUUUUUUU )
0*
bUUUU +
bUUUUUUU ,
bUUUU -
bUUUUUUU .
0/
00
11
12
b00 3
bUUUUUUUU 4
05
06
b00000000 7
#5000000
1*
1/
#10000000
0*
0/
#15000000
1*
1/
#20000000
1!
0"
0*
0/
10
01
#25000000
b00000000 $
b01 %
1&
b1000000 (
b1000000 )
1*
b0000 +
b1000000 ,
b0000 -
b1000000 .
1/
b01 3
b00000000 4
15
b00000001 7
#30000000
0*
0/
#35000000
1*
1/
b00000010 7
#40000000
0*
0/
#45000000
1*
1/
b00000011 7
#50000000
1"
0*
0/
11
#55000000
1*
1/
b00000100 7
#60000000
0*
0/
#65000000
1*
1/
b00000101 7
#70000000
0*
0/
#75000000
1*
1/
b00000110 7
#80000000
0*
0/
#85000000
1*
1/
b00000111 7
#90000000
0*
0/
#95000000
1*
1/
b00001000 7
#100000000
0*
0/
#105000000
1*
1/
b00001001 7
#110000000
0*
0/
#115000000
1*
1/
b00001010 7
#120000000
0*
0/
#125000000
1*
1/
b00001011 7
#130000000
0*
0/
#135000000
1*
1/
b00001100 7
#140000000
0*
0/
#145000000
1*
1/
b00001101 7
#150000000
0*
0/
#155000000
1*
1/
b00001110 7
#160000000
0*
0/
#165000000
1*
1/
b00001111 7
#170000000
0*
0/
#175000000
b10 %
0&
1'
1*
1/
b10 3
05
16
b00000000 7
#180000000
0*
0/
#185000000
1*
1/
b00000001 7
#190000000
0*
0/
#195000000
1*
1/
b00000010 7
#200000000
0#
0*
0/
02
#205000000
b00000011 $
b00 %
0'
b0110000 (
1*
b0011 +
b0110000 ,
1/
b00 3
b00000011 4
06
b00000011 7
#210000000
0*
0/
#215000000
1*
1/
b00000100 7
#220000000
1#
0*
0/
12
#225000000
1*
1/
b00000101 7
#230000000
0*
0/
#235000000
1*
1/
b00000110 7
#240000000
0*
0/
#245000000
1*
1/
b00000111 7
#250000000
0!
0*
0/
00
b00000000 7
#255000000
1*
1/
#260000000
0*
0/
#265000000
1*
1/
#270000000
1!
0*
0/
10
#275000000
1*
1/
b00000001 7
#280000000
0"
0*
0/
01
#285000000
b00000000 $
b01 %
1&
b1000000 (
1*
b0000 +
b1000000 ,
1/
b01 3
b00000000 4
15
b00000010 7
#290000000
0*
0/
#295000000
1*
1/
b00000011 7
#300000000
1"
0*
0/
11
#305000000
1*
1/
b00000100 7
#310000000
0*
0/
#315000000
1*
1/
b00000101 7
#320000000
0*
0/
#325000000
1*
1/
b00000110 7
#330000000
0*
0/
#335000000
1*
1/
b00000111 7
#340000000
0*
0/
#345000000
1*
1/
b00001000 7
#350000000
0#
0*
0/
02
#355000000
b11111111 $
b00 %
0&
b0001110 (
b0001110 )
1*
b1111 +
b0001110 ,
b1111 -
b0001110 .
1/
b00 3
b11111111 4
05
b11111111 7
#360000000
0*
0/
#365000000
1*
1/
b00000000 7
#370000000
1#
0*
0/
12
#375000000
1*
1/
b00000001 7
#380000000
0*
0/
#385000000
1*
1/
b00000010 7
#390000000
0*
0/
#395000000
1*
1/
b00000011 7
#400000000
0*
0/
#405000000
1*
1/
b00000100 7
#410000000
0*
0/
#415000000
1*
1/
b00000101 7
#420000000
0*
0/
#425000000
1*
1/
b00000110 7
#430000000
0*
0/
#435000000
1*
1/
b00000111 7
#440000000
0*
0/
#445000000
1*
1/
b00001000 7
#450000000
0*
0/
#455000000
1*
1/
b00001001 7
#460000000
0*
0/
#465000000
1*
1/
b00001010 7
#470000000
0*
0/
#475000000
1*
1/
b00001011 7
#480000000
0*
0/
#485000000
1*
1/
b00001100 7
#490000000
0*
0/
#495000000
1*
1/
b00001101 7
