Project01/traffic/counter.vhd
-- Quartus II VHDL Template
-- Binary Counter
-- modified by Maxwell S16

library ieee;
use ieee.std_logic_1164.all;
use ieee.numeric_std.all;

entity counter is

  port
    (
      clk         : in std_logic;
      reset	  : in std_logic;
      enable	  : in std_logic;
      q		  : out std_logic_vector (3 downto 0)
      );

end entity;

architecture rtl of counter is

  signal   cnt	: unsigned (3 downto 0);

begin

  process (clk)
  begin
    if reset = '1' then
      -- Reset the counter to 0
      cnt <= "0000";
    elsif (rising_edge(clk)) then
      if enable = '1' then
        -- Increment the counter if counting is enabled			   
        cnt <= cnt + 1;
      end if;
    end if;
  end process;

  q <= std_logic_vector(cnt);

end rtl;

Project01/traffic/traffic.vhd
-- Copyright (C) 1991-2012 Altera Corporation
-- Your use of Altera Corporation's design tools, logic functions 
-- and other software and tools, and its AMPP partner logic 
-- functions, and any output files from any of the foregoing 
-- (including device programming or simulation files), and any 
-- associated documentation or information are expressly subject 
-- to the terms and conditions of the Altera Program License 
-- Subscription Agreement, Altera MegaCore Function License 
-- Agreement, or other applicable license agreement, including, 
-- without limitation, that your use is for the sole purpose of 
-- programming logic devices manufactured by Altera and sold by 
-- Altera or its authorized distributors.  Please refer to the 
-- applicable agreement for further details.

-- PROGRAM		"Quartus II 32-bit"
-- VERSION		"Version 12.1 Build 177 11/07/2012 SJ Full Version"
-- CREATED		"Sun Sep 25 16:15:50 2022"

LIBRARY ieee;
USE ieee.std_logic_1164.all; 

LIBRARY work;

ENTITY traffic IS 
	PORT
	(
		clk :  IN  STD_LOGIC;
		enable :  IN  STD_LOGIC;
		reset :  IN  STD_LOGIC;
		NS_R :  OUT  STD_LOGIC;
		NS_G :  OUT  STD_LOGIC;
		NS_Y :  OUT  STD_LOGIC;
		EW_R :  OUT  STD_LOGIC;
		EW_G :  OUT  STD_LOGIC;
		EW_Y :  OUT  STD_LOGIC
	);
END traffic;

ARCHITECTURE bdf_type OF traffic IS 

COMPONENT counter
	PORT(clk : IN STD_LOGIC;
		 reset : IN STD_LOGIC;
		 enable : IN STD_LOGIC;
		 q : OUT STD_LOGIC_VECTOR(3 DOWNTO 0)
	);
END COMPONENT;

SIGNAL	q :  STD_LOGIC_VECTOR(3 DOWNTO 0);
SIGNAL	SYNTHESIZED_WIRE_0 :  STD_LOGIC;
SIGNAL	SYNTHESIZED_WIRE_1 :  STD_LOGIC;
SIGNAL	SYNTHESIZED_WIRE_2 :  STD_LOGIC;
SIGNAL	SYNTHESIZED_WIRE_3 :  STD_LOGIC;
SIGNAL	SYNTHESIZED_WIRE_4 :  STD_LOGIC;
SIGNAL	SYNTHESIZED_WIRE_5 :  STD_LOGIC;
SIGNAL	SYNTHESIZED_WIRE_6 :  STD_LOGIC;
SIGNAL	SYNTHESIZED_WIRE_7 :  STD_LOGIC;
SIGNAL	SYNTHESIZED_WIRE_8 :  STD_LOGIC;
SIGNAL	SYNTHESIZED_WIRE_9 :  STD_LOGIC;
SIGNAL	SYNTHESIZED_WIRE_10 :  STD_LOGIC;
SIGNAL	SYNTHESIZED_WIRE_11 :  STD_LOGIC;
SIGNAL	SYNTHESIZED_WIRE_12 :  STD_LOGIC;
SIGNAL	SYNTHESIZED_WIRE_13 :  STD_LOGIC;
SIGNAL	SYNTHESIZED_WIRE_14 :  STD_LOGIC;
SIGNAL	SYNTHESIZED_WIRE_15 :  STD_LOGIC;
SIGNAL	SYNTHESIZED_WIRE_16 :  STD_LOGIC;
SIGNAL	SYNTHESIZED_WIRE_17 :  STD_LOGIC;
SIGNAL	SYNTHESIZED_WIRE_18 :  STD_LOGIC;
SIGNAL	SYNTHESIZED_WIRE_19 :  STD_LOGIC;
SIGNAL	SYNTHESIZED_WIRE_20 :  STD_LOGIC;
SIGNAL	SYNTHESIZED_WIRE_21 :  STD_LOGIC;
SIGNAL	SYNTHESIZED_WIRE_22 :  STD_LOGIC;
SIGNAL	SYNTHESIZED_WIRE_23 :  STD_LOGIC;
SIGNAL	SYNTHESIZED_WIRE_24 :  STD_LOGIC;


BEGIN 



SYNTHESIZED_WIRE_14 <= NOT(q(1));



SYNTHESIZED_WIRE_15 <= NOT(q(0));



SYNTHESIZED_WIRE_19 <= NOT(q(3));



SYNTHESIZED_WIRE_20 <= NOT(q(2));



SYNTHESIZED_WIRE_21 <= NOT(q(3));



SYNTHESIZED_WIRE_22 <= NOT(q(2));



SYNTHESIZED_WIRE_23 <= NOT(q(3));



SYNTHESIZED_WIRE_24 <= NOT(q(1));



NS_Y <= SYNTHESIZED_WIRE_0 AND q(2) AND q(1);


SYNTHESIZED_WIRE_0 <= NOT(q(3));



EW_R <= SYNTHESIZED_WIRE_1 OR SYNTHESIZED_WIRE_2;


SYNTHESIZED_WIRE_1 <= SYNTHESIZED_WIRE_3 AND SYNTHESIZED_WIRE_4 AND SYNTHESIZED_WIRE_5;


NS_R <= SYNTHESIZED_WIRE_6 OR q(3);


SYNTHESIZED_WIRE_3 <= NOT(q(2));



SYNTHESIZED_WIRE_4 <= NOT(q(1));



SYNTHESIZED_WIRE_5 <= NOT(q(0));



EW_G <= SYNTHESIZED_WIRE_7 OR SYNTHESIZED_WIRE_8 OR SYNTHESIZED_WIRE_9;


SYNTHESIZED_WIRE_9 <= q(3) AND SYNTHESIZED_WIRE_10 AND q(0);


SYNTHESIZED_WIRE_7 <= q(3) AND SYNTHESIZED_WIRE_11 AND q(1);


SYNTHESIZED_WIRE_8 <= q(3) AND q(2) AND SYNTHESIZED_WIRE_12;


SYNTHESIZED_WIRE_10 <= NOT(q(2));



SYNTHESIZED_WIRE_6 <= SYNTHESIZED_WIRE_13 AND SYNTHESIZED_WIRE_14 AND SYNTHESIZED_WIRE_15;


SYNTHESIZED_WIRE_11 <= NOT(q(2));



SYNTHESIZED_WIRE_12 <= NOT(q(1));



EW_Y <= q(3) AND q(2) AND q(1);


SYNTHESIZED_WIRE_2 <= NOT(q(3));



SYNTHESIZED_WIRE_13 <= NOT(q(2));



b2v_inst50 : counter
PORT MAP(clk => clk,
		 reset => reset,
		 enable => enable,
		 q => q);


NS_G <= SYNTHESIZED_WIRE_16 OR SYNTHESIZED_WIRE_17 OR SYNTHESIZED_WIRE_18;


SYNTHESIZED_WIRE_18 <= SYNTHESIZED_WIRE_19 AND SYNTHESIZED_WIRE_20 AND q(0);


SYNTHESIZED_WIRE_16 <= SYNTHESIZED_WIRE_21 AND SYNTHESIZED_WIRE_22 AND q(1);


SYNTHESIZED_WIRE_17 <= SYNTHESIZED_WIRE_23 AND q(2) AND SYNTHESIZED_WIRE_24;


END bdf_type;

Project01/traffic/trafficbench.vhd
-- Stephanie R Taylor
-- Fall 2020
-- CS 232
--
-- test program for the traffic light simulation
-- shows how to create a clock using a loop

library ieee;
use ieee.std_logic_1164.all;
use ieee.numeric_std.all;

entity trafficbench is
end entity;

architecture test of trafficbench is
  constant num_cycles : integer := 16;  -- run for 40 clock cycles

  -- this circuit needs a clock, enable, and a reset
  -- for the counter
  signal clk    : std_logic := '1';
  signal enable : std_logic;
  signal reset  : std_logic;

  -- light signals
  signal NSred, NSyellow, NSgreen, EWred, EWyellow, EWgreen: std_logic;

  -- traffic component
  -- YOU MAY NEED TO MODIFY THIS PART!
  -- If the quartus-generated traffic.vhd puts
  -- the input and output signals in a different order, then
  -- you need to copy-paste that order into this file. (Grab
  -- the "port" code.) 
  component traffic
  port(
  		clk :  IN  STD_LOGIC;
		enable :  IN  STD_LOGIC;
		reset :  IN  STD_LOGIC;
		NS_R :  OUT  STD_LOGIC;
		NS_G :  OUT  STD_LOGIC;
		NS_Y :  OUT  STD_LOGIC;
		EW_R :  OUT  STD_LOGIC;
		EW_G :  OUT  STD_LOGIC;
		EW_Y :  OUT  STD_LOGIC);
  end component;

  begin

  -- start off with a short reset
  reset <= '1', '0' after 5 ns;

  enable <= '1';

  -- create a clock
  process begin
    for i in 1 to num_cycles loop
      clk <= not clk;
      wait for 5 ns;
      clk <= not clk;
      wait for 5 ns;
    end loop;
    wait;
  end process;

  -- port map the circuit
  -- Make sure the list of inputs here has signals declared above (all the ones here now have been).
  -- Also make sure the order matches that from the port definition of the traffic
  -- component.
  L0: traffic port map( clk, enable, reset, NSred, NSgreen, NSyellow, EWred, EWgreen, EWyellow );

end test;

Project01/traffic/trafficbench.vcd
$date
  Mon Sep 26 21:24:02 2022
$end
$version
  GHDL v0
$end
$timescale
  1 fs
$end
$scope module standard $end
$upscope $end
$scope module std_logic_1164 $end
$upscope $end
$scope module numeric_std $end
$upscope $end
$scope module trafficbench $end
$var reg 1 ! clk $end
$var reg 1 " enable $end
$var reg 1 # reset $end
$var reg 1 $ nsred $end
$var reg 1 % nsyellow $end
$var reg 1 & nsgreen $end
$var reg 1 ' ewred $end
$var reg 1 ( ewyellow $end
$var reg 1 ) ewgreen $end
$scope module l0 $end
$var reg 1 * clk $end
$var reg 1 + enable $end
$var reg 1 , reset $end
$var reg 1 - ns_r $end
$var reg 1 . ns_g $end
$var reg 1 / ns_y $end
$var reg 1 0 ew_r $end
$var reg 1 1 ew_g $end
$var reg 1 2 ew_y $end
$var reg 4 3 q[3:0] $end
$var reg 1 4 synthesized_wire_0 $end
$var reg 1 5 synthesized_wire_1 $end
$var reg 1 6 synthesized_wire_2 $end
$var reg 1 7 synthesized_wire_3 $end
$var reg 1 8 synthesized_wire_4 $end
$var reg 1 9 synthesized_wire_5 $end
$var reg 1 : synthesized_wire_6 $end
$var reg 1 ; synthesized_wire_7 $end
$var reg 1 < synthesized_wire_8 $end
$var reg 1 = synthesized_wire_9 $end
$var reg 1 > synthesized_wire_10 $end
$var reg 1 ? synthesized_wire_11 $end
$var reg 1 @ synthesized_wire_12 $end
$var reg 1 A synthesized_wire_13 $end
$var reg 1 B synthesized_wire_14 $end
$var reg 1 C synthesized_wire_15 $end
$var reg 1 D synthesized_wire_16 $end
$var reg 1 E synthesized_wire_17 $end
$var reg 1 F synthesized_wire_18 $end
$var reg 1 G synthesized_wire_19 $end
$var reg 1 H synthesized_wire_20 $end
$var reg 1 I synthesized_wire_21 $end
$var reg 1 J synthesized_wire_22 $end
$var reg 1 K synthesized_wire_23 $end
$var reg 1 L synthesized_wire_24 $end
$scope module b2v_inst50 $end
$var reg 1 M clk $end
$var reg 1 N reset $end
$var reg 1 O enable $end
$var reg 4 P q[3:0] $end
$var reg 4 Q cnt[3:0] $end
$upscope $end
$upscope $end
$upscope $end
$enddefinitions $end
#0
0!
1"
1#
1$
0%
0&
1'
0(
0)
0*
1+
1,
1-
0.
0/
10
01
02
b0000 3
14
15
16
17
18
19
1:
0;
0<
0=
1>
1?
1@
1A
1B
1C
0D
0E
0F
1G
1H
1I
1J
1K
1L
0M
1N
1O
b0000 P
b0000 Q
#5000000
1!
0#
0$
1&
1*
0,
0-
1.
b0001 3
05
09
0:
0C
1F
1M
0N
b0001 P
b0001 Q
#10000000
0!
0*
0M
#15000000
1!
1*
b0010 3
08
19
0@
0B
1C
1D
0F
0L
1M
b0010 P
b0010 Q
#20000000
0!
0*
0M
#25000000
1!
1*
b0011 3
09
0C
1F
1M
b0011 P
b0011 Q
#30000000
0!
0*
0M
#35000000
1!
1&
1*
1.
b0100 3
07
18
19
0>
0?
1@
0A
1B
1C
0D
1E
0F
0H
0J
1L
1M
b0100 P
b0100 Q
#40000000
0!
0*
0M
#45000000
1!
1*
b0101 3
09
0C
1M
b0101 P
b0101 Q
#50000000
0!
0*
0M
#55000000
1!
1%
0&
1*
0.
1/
b0110 3
08
19
0@
0B
1C
0E
0L
1M
b0110 P
b0110 Q
#60000000
0!
0*
0M
#65000000
1!
1*
b0111 3
09
0C
1M
b0111 P
b0111 Q
#70000000
0!
0*
0M
#75000000
1!
1$
0%
1'
1*
1-
0/
10
b1000 3
04
15
06
17
18
19
1:
1>
1?
1@
1A
1B
1C
0G
1H
0I
1J
0K
1L
1M
b1000 P
b1000 Q
#80000000
0!
0*
0M
#85000000
1!
0'
1)
1*
00
11
b1001 3
05
09
0:
1=
0C
1M
b1001 P
b1001 Q
#90000000
0!
0*
0M
#95000000
1!
1*
b1010 3
08
19
1;
0=
0@
0B
1C
0L
1M
b1010 P
b1010 Q
#100000000
0!
0*
0M
#105000000
1!
1*
b1011 3
09
1=
0C
1M
b1011 P
b1011 Q
#110000000
0!
0*
0M
#115000000
1!
1)
1*
11
b1100 3
07
18
19
0;
1<
0=
0>
0?
1@
0A
1B
1C
0H
0J
1L
1M
b1100 P
b1100 Q
#120000000
0!
0*
0M
#125000000
1!
1*
b1101 3
09
0C
1M
b1101 P
b1101 Q
#130000000
0!
0*
0M
#135000000
1!
1(
0)
1*
01
12
b1110 3
08
19
0<
0@
0B
1C
0L
1M
b1110 P
b1110 Q
#140000000
0!
0*
0M
#145000000
1!
1*
b1111 3
09
0C
1M
b1111 P
b1111 Q
#150000000
0!
0*
0M
#155000000
1!
1$
1'
0(
1*
1-
10
02
b0000 3
14
15
16
17
18
19
1:
1>
1?
1@
1A
1B
1C
1G
1H
1I
1J
1K
1L
1M
b0000 P
b0000 Q
